{"v":"4.8.0","meta":{"g":"LottieFiles AE 3.5.8","a":"","k":"","d":"","tc":""},"fr":30,"ip":0,"op":120,"w":500,"h":500,"nm":"Assembling puzzle Lottie JSON animation","ddd":0,"assets":[{"id":"comp_0","layers":[{"ddd":0,"ind":1,"ty":4,"nm":"Hand 4","sr":1,"ks":{"o":{"a":0,"k":100,"ix":11},"r":{"a":0,"k":0,"ix":10},"p":{"a":0,"k":[45.084,309.344,0],"ix":2},"a":{"a":0,"k":[45.084,309.344,0],"ix":1},"s":{"a":0,"k":[100,100,100],"ix":6}},"ao":0,"shapes":[{"ty":"gr","it":[{"ty":"gr","it":[{"ind":0,"ty":"sh","ix":1,"ks":{"a":0,"k":{"i":[[-7.175,2.911],[-7.569,2.853],[-7.829000000000001,2.218],[5.487,-2.722],[7.761,-2.737],[7.619,-1.9429999999999998],[-2.9479999999999995,-0.734]],"o":[[-7.431,2.911],[-7.8500000000000005,2.533],[-3.4640000000000004,-1.6109999999999998],[7.516,-2.9379999999999997],[7.818,-2.189],[6.303,-1.8039999999999998],[-7.0569999999999995,2.87]],"v":[[-7.292,2.911],[-7.668,2.741],[-7.621,2.035],[7.239,-2.908],[7.789,-2.463],[7.345,-1.914],[-6.962,2.787]],"c":true},"ix":2},"nm":"Path 1","mn":"ADBE Vector Shape - Group","hd":false,"_render":true},{"ty":"fl","c":{"a":0,"k":[0.8409,0.5339,0.2991,1],"ix":4},"o":{"a":0,"k":100,"ix":5},"r":1,"bm":0,"nm":"Fill 1","mn":"ADBE Vector Graphic - Fill","hd":false,"_render":true},{"ty":"tr","p":{"a":0,"k":[0,0],"ix":2},"a":{"a":0,"k":[0,0],"ix":1},"s":{"a":0,"k":[100,100],"ix":3},"r":{"a":0,"k":0,"ix":6},"o":{"a":0,"k":100,"ix":7},"sk":{"a":0,"k":0,"ix":4},"sa":{"a":0,"k":0,"ix":5},"nm":"Transform","_render":true}],"nm":"Group 1","np":2,"cix":2,"bm":0,"ix":1,"mn":"ADBE Vector Group","hd":false,"_render":true},{"ty":"tr","p":{"a":0,"k":[53.64,271.582],"ix":2},"a":{"a":0,"k":[0,0],"ix":1},"s":{"a":0,"k":[100,100],"ix":3},"r":{"a":0,"k":0,"ix":6},"o":{"a":0,"k":100,"ix":7},"sk":{"a":0,"k":0,"ix":4},"sa":{"a":0,"k":0,"ix":5},"nm":"Transform","_render":true}],"nm":"Group 1","np":1,"cix":2,"bm":0,"ix":1,"mn":"ADBE Vector Group","hd":false,"_render":true},{"ty":"gr","it":[{"ty":"gr","it":[{"ind":0,"ty":"sh","ix":1,"ks":{"a":0,"k":{"i":[[-2.439,1.666],[-2.828,1.6119999999999999],[-3.104,0.9890000000000001],[0.4979999999999998,-1.454],[3.029,-1.492],[2.886,-0.6970000000000001],[-0.9000000000000001,0.29899999999999993]],"o":[[-2.695,1.666],[-3.115,1.3059999999999998],[-1.423,-0.5789999999999998],[2.787,-1.693],[3.086,-0.944],[0.8160000000000001,-0.48200000000000004],[-2.317,1.621]],"v":[[-2.561,1.666],[-2.927,1.507],[-2.902,0.801],[2.509,-1.663],[3.058,-1.218],[2.612,-0.669],[-2.22,1.531]],"c":true},"ix":2},"nm":"Path 1","mn":"ADBE Vector Shape - Group","hd":false,"_render":true},{"ty":"fl","c":{"a":0,"k":[0.8409,0.5339,0.2991,1],"ix":4},"o":{"a":0,"k":100,"ix":5},"r":1,"bm":0,"nm":"Fill 1","mn":"ADBE Vector Graphic - Fill","hd":false,"_render":true},{"ty":"tr","p":{"a":0,"k":[0,0],"ix":2},"a":{"a":0,"k":[0,0],"ix":1},"s":{"a":0,"k":[100,100],"ix":3},"r":{"a":0,"k":0,"ix":6},"o":{"a":0,"k":100,"ix":7},"sk":{"a":0,"k":0,"ix":4},"sa":{"a":0,"k":0,"ix":5},"nm":"Transform","_render":true}],"nm":"Group 1","np":2,"cix":2,"bm":0,"ix":1,"mn":"ADBE Vector Group","hd":false,"_render":true},{"ty":"tr","p":{"a":0,"k":[68.286,302.515],"ix":2},"a":{"a":0,"k":[0,0],"ix":1},"s":{"a":0,"k":[100,100],"ix":3},"r":{"a":0,"k":0,"ix":6},"o":{"a":0,"k":100,"ix":7},"sk":{"a":0,"k":0,"ix":4},"sa":{"a":0,"k":0,"ix":5},"nm":"Transform","_render":true}],"nm":"Group 2","np":1,"cix":2,"bm":0,"ix":2,"mn":"ADBE Vector Group","hd":false,"_render":true},{"ty":"gr","it":[{"ty":"gr","it":[{"ind":0,"ty":"sh","ix":1,"ks":{"a":0,"k":{"i":[[9.056999999999999,4.322],[8.611,4.204],[6.143000000000001,-1.885],[-5.952,-2.8689999999999998],[-9.274,-1.061],[-9.494,-1.8390000000000002],[-0.29000000000000004,-5.027],[8.141,0.3809999999999998],[9.439,4.1819999999999995]],"o":[[8.798,4.322],[7.25,0.847],[-0.34399999999999986,-3.9939999999999998],[-8.966,-0.9899999999999999],[-9.566,-1.53],[-6.294,-3.834],[6.895,-2.692],[9.562999999999999,3.891],[9.121,4.31]],"v":[[8.995,4.322],[8.532,4.01],[2.995,-2.908],[-8.731,-1.136],[-9.42,-1.296],[-9.26,-1.985],[3.304,-3.859],[9.459,3.635],[9.183,4.286]],"c":true},"ix":2},"nm":"Path 1","mn":"ADBE Vector Shape - Group","hd":false,"_render":true},{"ty":"fl","c":{"a":0,"k":[0.8409,0.5339,0.2991,1],"ix":4},"o":{"a":0,"k":100,"ix":5},"r":1,"bm":0,"nm":"Fill 1","mn":"ADBE Vector Graphic - Fill","hd":false,"_render":true},{"ty":"tr","p":{"a":0,"k":[0,0],"ix":2},"a":{"a":0,"k":[0,0],"ix":1},"s":{"a":0,"k":[100,100],"ix":3},"r":{"a":0,"k":0,"ix":6},"o":{"a":0,"k":100,"ix":7},"sk":{"a":0,"k":0,"ix":4},"sa":{"a":0,"k":0,"ix":5},"nm":"Transform","_render":true}],"nm":"Group 1","np":2,"cix":2,"bm":0,"ix":1,"mn":"ADBE Vector Group","hd":false,"_render":true},{"ty":"tr","p":{"a":0,"k":[68.639,292.588],"ix":2},"a":{"a":0,"k":[0,0],"ix":1},"s":{"a":0,"k":[100,100],"ix":3},"r":{"a":0,"k":0,"ix":6},"o":{"a":0,"k":100,"ix":7},"sk":{"a":0,"k":0,"ix":4},"sa":{"a":0,"k":0,"ix":5},"nm":"Transform","_render":true}],"nm":"Group 3","np":1,"cix":2,"bm":0,"ix":3,"mn":"ADBE Vector Group","hd":false,"_render":true},{"ty":"gr","it":[{"ty":"gr","it":[{"ind":0,"ty":"sh","ix":1,"ks":{"a":0,"k":{"i":[[11.786999999999999,2.708],[11.395,2.6519999999999997],[-3.139000000000001,-3.1510000000000002],[-11.949,2.012],[-12.165999999999999,1.234],[6.828999999999999,-3.927],[12.208,2.395]],"o":[[11.530999999999999,2.708],[6.409,-2.8980000000000006],[-11.641,2.086],[-12.238999999999999,1.542],[-3.251999999999999,-4.254],[12.225,2.079],[11.907,2.666]],"v":[[11.668,2.708],[11.296,2.542],[-11.406,1.94],[-12.094,1.776],[-11.931,1.089],[12.04,1.874],[12.002,2.58]],"c":true},"ix":2},"nm":"Path 1","mn":"ADBE Vector Shape - Group","hd":false,"_render":true},{"ty":"fl","c":{"a":0,"k":[0.8409,0.5339,0.2991,1],"ix":4},"o":{"a":0,"k":100,"ix":5},"r":1,"bm":0,"nm":"Fill 1","mn":"ADBE Vector Graphic - Fill","hd":false,"_render":true},{"ty":"tr","p":{"a":0,"k":[0,0],"ix":2},"a":{"a":0,"k":[0,0],"ix":1},"s":{"a":0,"k":[100,100],"ix":3},"r":{"a":0,"k":0,"ix":6},"o":{"a":0,"k":100,"ix":7},"sk":{"a":0,"k":0,"ix":4},"sa":{"a":0,"k":0,"ix":5},"nm":"Transform","_render":true}],"nm":"Group 1","np":2,"cix":2,"bm":0,"ix":1,"mn":"ADBE Vector Group","hd":false,"_render":true},{"ty":"tr","p":{"a":0,"k":[63.292,279.048],"ix":2},"a":{"a":0,"k":[0,0],"ix":1},"s":{"a":0,"k":[100,100],"ix":3},"r":{"a":0,"k":0,"ix":6},"o":{"a":0,"k":100,"ix":7},"sk":{"a":0,"k":0,"ix":4},"sa":{"a":0,"k":0,"ix":5},"nm":"Transform","_render":true}],"nm":"Group 4","np":1,"cix":2,"bm":0,"ix":4,"mn":"ADBE Vector Group","hd":false,"_render":true},{"ty":"gr","it":[{"ty":"gr","it":[{"ind":0,"ty":"sh","ix":1,"ks":{"a":0,"k":{"i":[[1.669,7.064],[1.19,6.891],[-0.807,-4.888],[-0.9209999999999999,-5.556],[-1.391,-6.09],[-2.064,-6.157],[-2.028,-6.965],[-0.536,-6.797],[0.11299999999999999,-5.445],[2.135,6.48],[1.997,7.011]],"o":[[1.401,7.064],[1.148,6.648],[-0.8630000000000001,-5.216],[-1.195,-5.977],[-1.793,-5.997],[-2.193,-6.696],[-1.121,-7.182],[0.030000000000000027,-5.928999999999999],[0.179,-5.056],[2.1809999999999996,6.752000000000001],[1.697,7.062]],"v":[[1.641,7.064],[1.148,6.648],[-0.807,-4.888],[-1.079,-5.798],[-1.525,-6.058],[-2.128,-6.427],[-1.759,-7.03],[-0.241,-6.345],[0.179,-5.056],[2.135,6.48],[1.725,7.057]],"c":true},"ix":2},"nm":"Path 1","mn":"ADBE Vector Shape - Group","hd":false,"_render":true},{"ty":"fl","c":{"a":0,"k":[0.8409,0.5339,0.2991,1],"ix":4},"o":{"a":0,"k":100,"ix":5},"r":1,"bm":0,"nm":"Fill 1","mn":"ADBE Vector Graphic - Fill","hd":false,"_render":true},{"ty":"tr","p":{"a":0,"k":[0,0],"ix":2},"a":{"a":0,"k":[0,0],"ix":1},"s":{"a":0,"k":[100,100],"ix":3},"r":{"a":0,"k":0,"ix":6},"o":{"a":0,"k":100,"ix":7},"sk":{"a":0,"k":0,"ix":4},"sa":{"a":0,"k":0,"ix":5},"nm":"Transform","_render":true}],"nm":"Group 1","np":2,"cix":2,"bm":0,"ix":1,"mn":"ADBE Vector Group","hd":false,"_render":true},{"ty":"tr","p":{"a":0,"k":[65.369,306.95],"ix":2},"a":{"a":0,"k":[0,0],"ix":1},"s":{"a":0,"k":[100,100],"ix":3},"r":{"a":0,"k":0,"ix":6},"o":{"a":0,"k":100,"ix":7},"sk":{"a":0,"k":0,"ix":4},"sa":{"a":0,"k":0,"ix":5},"nm":"Transform","_render":true}],"nm":"Group 5","np":1,"cix":2,"bm":0,"ix":5,"mn":"ADBE Vector Group","hd":false,"_render":true},{"ty":"gr","it":[{"ty":"gr","it":[{"ty":"gr","it":[{"ind":0,"ty":"sh","ix":1,"ks":{"a":0,"k":{"i":[[1.405,-0.505],[0.654,-3.106],[-0.915,-5.305],[0.582,5.462],[1.838,2.776]],"o":[[0.87,-2.242],[-0.216,-4.636],[-1.78,-5.462],[1.2029999999999998,4.151999999999999],[1.736,0.391]],"v":[[1.129,-1.401],[0.219,-3.871],[-1.78,-5.462],[0.582,5.462],[1.776,1.328]],"c":true},"ix":2},"nm":"Path 1","mn":"ADBE Vector Shape - Group","hd":false,"_render":true},{"ty":"fl","c":{"a":0,"k":[0.3333,0,0,1],"ix":4},"o":{"a":0,"k":100,"ix":5},"r":1,"bm":0,"nm":"Fill 1","mn":"ADBE Vector Graphic - Fill","hd":false,"_render":true},{"ty":"tr","p":{"a":0,"k":[0,0],"ix":2},"a":{"a":0,"k":[0,0],"ix":1},"s":{"a":0,"k":[100,100],"ix":3},"r":{"a":0,"k":0,"ix":6},"o":{"a":0,"k":100,"ix":7},"sk":{"a":0,"k":0,"ix":4},"sa":{"a":0,"k":0,"ix":5},"nm":"Transform","_render":true}],"nm":"Group 1","np":2,"cix":2,"bm":0,"ix":1,"mn":"ADBE Vector Group","hd":false,"_render":true},{"ty":"tr","p":{"a":0,"k":[66.426,305.748],"ix":2},"a":{"a":0,"k":[0,0],"ix":1},"s":{"a":0,"k":[100,100],"ix":3},"r":{"a":0,"k":0,"ix":6},"o":{"a":0,"k":100,"ix":7},"sk":{"a":0,"k":0,"ix":4},"sa":{"a":0,"k":0,"ix":5},"nm":"Transform","_render":true}],"nm":"Group 1","np":1,"cix":2,"bm":0,"ix":1,"mn":"ADBE Vector Group","hd":false,"_render":true},{"ty":"tr","p":{"a":0,"k":[66.426,305.748],"ix":2},"a":{"a":0,"k":[66.426,305.748],"ix":1},"s":{"a":0,"k":[100,100],"ix":3},"r":{"a":0,"k":0,"ix":6},"o":{"a":0,"k":100,"ix":7},"sk":{"a":0,"k":0,"ix":4},"sa":{"a":0,"k":0,"ix":5},"nm":"Transform","_render":true}],"nm":"Group 6","np":1,"cix":2,"bm":0,"ix":6,"mn":"ADBE Vector Group","hd":false,"_render":true},{"ty":"gr","it":[{"ty":"gr","it":[{"ind":0,"ty":"sh","ix":1,"ks":{"a":0,"k":{"i":[[-4.763,11.36],[-10.471,-29.202],[6.465000000000001,-72.569],[14.042,-71.456],[4.237,-46.362],[5.574,-37.002],[14.711000000000002,-41.683],[32.763,-33.214],[36.551,-24.076],[34.769,-12.934],[36.551,-6.693],[23.849,1.998],[27.333,19.322000000000003],[5.3420000000000005,73.39500000000001],[-36.79,73.346],[-11.408,23.738]],"o":[[-4.763,11.36],[-11.809000000000001,-49.260000000000005],[10.923000000000002,-73.907],[12.26,-60.757999999999996],[4.237,-46.362],[5.574,-37.002],[30.757,-37.671],[32.094,-28.088],[36.997,-16.054000000000002],[34.769,-12.934],[33.431,-1.791],[23.849,1.998],[18.593,25.213],[5.636,73.346],[-36.79,73.346],[-7.8420000000000005,16.606]],"v":[[-4.763,11.36],[-11.14,-39.231],[8.694,-73.238],[13.151,-66.107],[4.237,-46.362],[5.574,-37.002],[22.734,-39.677],[32.094,-28.088],[36.774,-20.065],[34.769,-12.934],[34.991,-4.242],[23.849,1.998],[18.593,25.213],[5.636,73.346],[-36.79,73.346],[-9.625,20.172]],"c":true},"ix":2},"nm":"Path 1","mn":"ADBE Vector Shape - Group","hd":false,"_render":true},{"ty":"fl","c":{"a":0,"k":[0.9925,0.831,0.7075,1],"ix":4},"o":{"a":0,"k":100,"ix":5},"r":1,"bm":0,"nm":"Fill 1","mn":"ADBE Vector Graphic - Fill","hd":false,"_render":true},{"ty":"tr","p":{"a":0,"k":[0,0],"ix":2},"a":{"a":0,"k":[0,0],"ix":1},"s":{"a":0,"k":[100,100],"ix":3},"r":{"a":0,"k":0,"ix":6},"o":{"a":0,"k":100,"ix":7},"sk":{"a":0,"k":0,"ix":4},"sa":{"a":0,"k":0,"ix":5},"nm":"Transform","_render":true}],"nm":"Group 1","np":2,"cix":2,"bm":0,"ix":1,"mn":"ADBE Vector Group","hd":false,"_render":true},{"ty":"tr","p":{"a":0,"k":[42.866,309.344],"ix":2},"a":{"a":0,"k":[0,0],"ix":1},"s":{"a":0,"k":[100,100],"ix":3},"r":{"a":0,"k":0,"ix":6},"o":{"a":0,"k":100,"ix":7},"sk":{"a":0,"k":0,"ix":4},"sa":{"a":0,"k":0,"ix":5},"nm":"Transform","_render":true}],"nm":"Group 7","np":1,"cix":2,"bm":0,"ix":7,"mn":"ADBE Vector Group","hd":false,"_render":true},{"ty":"gr","it":[{"ty":"gr","it":[{"ind":0,"ty":"sh","ix":1,"ks":{"a":0,"k":{"i":[[-4.979,-15.37],[0.9310000000000003,-14.985],[3.479,-6.061],[9.467,-1.9240000000000004],[5.155,10.779],[7.363,15.37],[-3.834,15.193],[-8.032,-7.127]],"o":[[-4.979,-15.37],[2.837,-8.879],[3.479,-6.061],[7.304,7.596],[5.155,10.779],[7.363,15.37],[-3.834,15.193],[-8.032,-7.127]],"v":[[-4.979,-15.37],[2.837,-8.879],[3.479,-6.061],[7.708,5.819],[5.155,10.779],[7.363,15.37],[-3.834,15.193],[-8.032,-7.127]],"c":true},"ix":2},"nm":"Path 1","mn":"ADBE Vector Shape - Group","hd":false,"_render":true},{"ty":"fl","c":{"a":0,"k":[0.3333,0,0,1],"ix":4},"o":{"a":0,"k":100,"ix":5},"r":1,"bm":0,"nm":"Fill 1","mn":"ADBE Vector Graphic - Fill","hd":false,"_render":true},{"ty":"tr","p":{"a":0,"k":[0,0],"ix":2},"a":{"a":0,"k":[0,0],"ix":1},"s":{"a":0,"k":[100,100],"ix":3},"r":{"a":0,"k":0,"ix":6},"o":{"a":0,"k":100,"ix":7},"sk":{"a":0,"k":0,"ix":4},"sa":{"a":0,"k":0,"ix":5},"nm":"Transform","_render":true}],"nm":"Group 1","np":2,"cix":2,"bm":0,"ix":1,"mn":"ADBE Vector Group","hd":false,"_render":true},{"ty":"tr","p":{"a":0,"k":[76.06,287.317],"ix":2},"a":{"a":0,"k":[0,0],"ix":1},"s":{"a":0,"k":[100,100],"ix":3},"r":{"a":0,"k":0,"ix":6},"o":{"a":0,"k":100,"ix":7},"sk":{"a":0,"k":0,"ix":4},"sa":{"a":0,"k":0,"ix":5},"nm":"Transform","_render":true}],"nm":"Group 8","np":1,"cix":2,"bm":0,"ix":8,"mn":"ADBE Vector Group","hd":false,"_render":true},{"ty":"gr","it":[{"ty":"gr","it":[{"ind":0,"ty":"sh","ix":1,"ks":{"a":0,"k":{"i":[[-1.765,-14.012],[1.408,-14.181],[-2.733,14.013],[-2.733,-2.087]],"o":[[-1.765,-14.012],[3.772,-3.712999999999999],[-2.733,14.013],[-2.733,-2.087]],"v":[[-1.765,-14.012],[2.59,-8.947],[-2.733,14.013],[-2.733,-2.087]],"c":true},"ix":2},"nm":"Path 1","mn":"ADBE Vector Shape - Group","hd":false,"_render":true},{"ty":"fl","c":{"a":0,"k":[0.3333,0,0,1],"ix":4},"o":{"a":0,"k":100,"ix":5},"r":1,"bm":0,"nm":"Fill 1","mn":"ADBE Vector Graphic - Fill","hd":false,"_render":true},{"ty":"tr","p":{"a":0,"k":[0,0],"ix":2},"a":{"a":0,"k":[0,0],"ix":1},"s":{"a":0,"k":[100,100],"ix":3},"r":{"a":0,"k":0,"ix":6},"o":{"a":0,"k":100,"ix":7},"sk":{"a":0,"k":0,"ix":4},"sa":{"a":0,"k":0,"ix":5},"nm":"Transform","_render":true}],"nm":"Group 1","np":2,"cix":2,"bm":0,"ix":1,"mn":"ADBE Vector Group","hd":false,"_render":true},{"ty":"tr","p":{"a":0,"k":[55.406,251.404],"ix":2},"a":{"a":0,"k":[0,0],"ix":1},"s":{"a":0,"k":[100,100],"ix":3},"r":{"a":0,"k":0,"ix":6},"o":{"a":0,"k":100,"ix":7},"sk":{"a":0,"k":0,"ix":4},"sa":{"a":0,"k":0,"ix":5},"nm":"Transform","_render":true}],"nm":"Group 9","np":1,"cix":2,"bm":0,"ix":9,"mn":"ADBE Vector Group","hd":false,"_render":true}],"ip":0,"op":120,"st":0,"bm":0,"completed":true},{"ddd":0,"ind":2,"ty":4,"nm":"Hand 3","sr":1,"ks":{"o":{"a":0,"k":100,"ix":11},"r":{"a":0,"k":0,"ix":10},"p":{"a":0,"k":[95.358,255.069,0],"ix":2},"a":{"a":0,"k":[95.358,255.069,0],"ix":1},"s":{"a":0,"k":[100,100,100],"ix":6}},"ao":0,"shapes":[{"ty":"gr","it":[{"ty":"gr","it":[{"ind":0,"ty":"sh","ix":1,"ks":{"a":0,"k":{"i":[[10.27,-16.058],[-15.953,3.2250000000000014],[-0.732,16.236],[-12.094000000000001,15.609],[14.704,-16.273]],"o":[[9.418,-16.236],[-14.667,16.236],[-0.732,16.236],[-0.5179999999999998,-3.3390000000000004],[14.718,-15.767000000000001]],"v":[[9.418,-16.236],[-14.667,16.236],[-0.732,16.236],[-6.306,6.135],[14.715,-15.874]],"c":true},"ix":2},"nm":"Path 1","mn":"ADBE Vector Shape - Group","hd":false,"_render":true},{"ty":"fl","c":{"a":0,"k":[1,1,1,1],"ix":4},"o":{"a":0,"k":100,"ix":5},"r":1,"bm":0,"nm":"Fill 1","mn":"ADBE Vector Graphic - Fill","hd":false,"_render":true},{"ty":"tr","p":{"a":0,"k":[0,0],"ix":2},"a":{"a":0,"k":[0,0],"ix":1},"s":{"a":0,"k":[100,100],"ix":3},"r":{"a":0,"k":0,"ix":6},"o":{"a":0,"k":100,"ix":7},"sk":{"a":0,"k":0,"ix":4},"sa":{"a":0,"k":0,"ix":5},"nm":"Transform","_render":true}],"nm":"Group 1","np":2,"cix":2,"bm":0,"ix":1,"mn":"ADBE Vector Group","hd":false,"_render":true},{"ty":"tr","p":{"a":0,"k":[118.459,286.451],"ix":2},"a":{"a":0,"k":[0,0],"ix":1},"s":{"a":0,"k":[100,100],"ix":3},"r":{"a":0,"k":0,"ix":6},"o":{"a":0,"k":100,"ix":7},"sk":{"a":0,"k":0,"ix":4},"sa":{"a":0,"k":0,"ix":5},"nm":"Transform","_render":true}],"nm":"Group 1","np":1,"cix":2,"bm":0,"ix":1,"mn":"ADBE Vector Group","hd":false,"_render":true},{"ty":"gr","it":[{"ty":"gr","it":[{"ind":0,"ty":"sh","ix":1,"ks":{"a":0,"k":{"i":[[23.195,-42.568],[27.910000000000004,-34.146],[-6.034000000000001,-2.4640000000000004],[-42.619,23.183],[-42.619,42.568],[-10.937999999999999,38.534],[1.9639999999999986,-4.915000000000001],[42.619,-42.568],[23.195,-42.568]],"o":[[23.195,-42.568],[6.412000000000001,-19.436],[-10.938,20.542],[-42.619,23.183],[-42.619,42.568],[1.1320000000000006,9.416000000000002],[22.064,-24.905],[42.619,-42.568],[23.195,-42.568]],"v":[[23.195,-42.568],[17.161,-26.791],[-8.486,9.039],[-42.619,23.183],[-42.619,42.568],[-4.903,23.975],[12.014,-14.91],[42.619,-42.568],[23.195,-42.568]],"c":false},"ix":2},"nm":"Path 1","mn":"ADBE Vector Shape - Group","hd":false,"_render":true},{"ty":"fl","c":{"a":0,"k":[1,1,1,1],"ix":4},"o":{"a":0,"k":100,"ix":5},"r":1,"bm":0,"nm":"Fill 1","mn":"ADBE Vector Graphic - Fill","hd":false,"_render":true},{"ty":"tr","p":{"a":0,"k":[0,0],"ix":2},"a":{"a":0,"k":[0,0],"ix":1},"s":{"a":0,"k":[100,100],"ix":3},"r":{"a":0,"k":0,"ix":6},"o":{"a":0,"k":100,"ix":7},"sk":{"a":0,"k":0,"ix":4},"sa":{"a":0,"k":0,"ix":5},"nm":"Transform","_render":true}],"nm":"Group 1","np":2,"cix":2,"bm":0,"ix":1,"mn":"ADBE Vector Group","hd":false,"_render":true},{"ty":"tr","p":{"a":0,"k":[95.358,250.018],"ix":2},"a":{"a":0,"k":[0,0],"ix":1},"s":{"a":0,"k":[100,100],"ix":3},"r":{"a":0,"k":0,"ix":6},"o":{"a":0,"k":100,"ix":7},"sk":{"a":0,"k":0,"ix":4},"sa":{"a":0,"k":0,"ix":5},"nm":"Transform","_render":true}],"nm":"Group 2","np":1,"cix":2,"bm":0,"ix":2,"mn":"ADBE Vector Group","hd":false,"_render":true}],"ip":0,"op":120,"st":0,"bm":0,"completed":true},{"ddd":0,"ind":3,"ty":4,"nm":"Hand 2","sr":1,"ks":{"o":{"a":0,"k":100,"ix":11},"r":{"a":0,"k":0,"ix":10},"p":{"a":0,"k":[100.291,239.39,0],"ix":2},"a":{"a":0,"k":[0,0,0],"ix":1},"s":{"a":0,"k":[100,100,100],"ix":6}},"ao":0,"shapes":[{"ty":"gr","it":[{"ind":0,"ty":"sh","ix":1,"ks":{"a":0,"k":{"i":[[45.117000000000004,6.090999999999999],[47.618,-27.657],[45.7,-31.94],[10.031,-31.94],[10.849,-38.954],[10.847,-38.954],[13.538,-44.464],[6.5600000000000005,-63.297],[-17.637,-56.319],[-16.531000000000002,-41.121],[-13.427,-32.873000000000005],[-43.335,-31.94],[-47.618,-30.022],[-47.618,59.014],[-45.7,63.297],[43.335,63.297],[47.618,61.379000000000005],[47.618,27.998],[45.143,26.215],[40.497,28.272],[34.766,31.266],[15.75,24.288],[22.729,0.091],[37.597,1.085],[40.093,2.781]],"o":[[47.618,3.066],[47.618,-30.022],[43.335,-31.94],[7.939,-34.556000000000004],[10.849,-38.954],[12.545,-41.45],[13.538,-56.319],[-10.658,-63.297],[-17.637,-44.286],[-12.995000000000001,-34.821],[-13.975,-31.94],[-45.7,-31.94],[-47.618,-27.657],[-47.618,61.379000000000005],[-43.335,63.297],[45.7,63.297],[47.618,59.014],[47.022000000000006,27.394000000000002],[40.498,28.288],[37.924,30.147],[22.729,31.266],[15.75,7.07],[34.584,0.091],[40.093,2.783],[40.093,2.781]],"v":[[47.618,3.066],[47.618,-27.657],[43.335,-31.94],[10.031,-31.94],[10.849,-38.954],[10.847,-38.954],[13.538,-47.71],[-2.049,-63.297],[-17.637,-47.71],[-14.659,-38.549],[-13.975,-31.94],[-43.335,-31.94],[-47.618,-27.657],[-47.618,59.014],[-43.335,63.297],[43.335,63.297],[47.618,59.014],[47.618,27.998],[40.498,28.288],[40.497,28.272],[31.338,31.266],[15.75,15.679],[31.338,0.091],[40.093,2.783],[40.093,2.781]],"c":true},"ix":2},"nm":"Path 1","mn":"ADBE Vector Shape - Group","hd":false,"_render":true},{"ty":"fl","c":{"a":0,"k":[1,0.26,0.556,1],"ix":4},"o":{"a":0,"k":100,"ix":5},"r":1,"bm":0,"nm":"Fill 1","mn":"ADBE Vector Graphic - Fill","hd":false,"_render":true},{"ty":"tr","p":{"a":0,"k":[0,0],"ix":2},"a":{"a":0,"k":[0,0],"ix":1},"s":{"a":0,"k":[100,100],"ix":3},"r":{"a":0,"k":0,"ix":6},"o":{"a":0,"k":100,"ix":7},"sk":{"a":0,"k":0,"ix":4},"sa":{"a":0,"k":0,"ix":5},"nm":"Transform","_render":true}],"nm":"Group 1","np":2,"cix":2,"bm":0,"ix":1,"mn":"ADBE Vector Group","hd":false,"_render":true}],"ip":0,"op":120,"st":0,"bm":0,"completed":true}]}],"layers":[{"ddd":0,"ind":1,"ty":4,"nm":"Hand 4","sr":1,"ks":{"o":{"a":1,"k":[{"i":{"x":[0.19],"y":[1]},"o":{"x":[0.333],"y":[0]},"t":23,"s":[0]},{"t":43,"s":[100]}],"ix":11},"r":{"a":0,"k":0,"ix":10},"p":{"a":1,"k":[{"i":{"x":0.19,"y":1},"o":{"x":0.333,"y":0},"t":23,"s":[493.893,484.072,0],"to":null,"ti":null},{"i":{"x":0.19,"y":0.19},"o":{"x":0.167,"y":0.167},"t":43,"s":[493.893,384.072,0],"to":null,"ti":null},{"i":{"x":0.19,"y":1},"o":{"x":0.167,"y":0},"t":70,"s":[493.893,384.072,0],"to":null,"ti":null},{"t":85,"s":[482.393,384.072,0]}],"ix":2},"a":{"a":0,"k":[493.893,384.072,0],"ix":1},"s":{"a":0,"k":[100,100,100],"ix":6}},"ao":0,"shapes":[{"ty":"gr","it":[{"ind":0,"ty":"sh","ix":1,"ks":{"a":0,"k":{"i":[[-18.663,-47.628],[-18.346,-26.989],[15.589,0.28500000000000014],[-23.738,47.628],[-4.059,47.628],[-5.977,39.14],[26.469,-8.912],[-11.052,-27.947999999999997],[-20.566,-47.608]],"o":[[-18.663,-47.628],[18.444,-12.4],[6.075000000000001,21.217],[-21.200000000000003,47.628],[-4.059,47.628],[21.933,5.042000000000002],[11.149000000000001,-24.770000000000003],[-3.44,-47.608],[-20.566,-47.608]],"v":[[-18.663,-47.628],[0.049,-19.695],[10.832,10.751],[-22.469,47.628],[-4.059,47.628],[7.978,22.091],[18.809,-16.841],[-3.44,-47.608],[-20.566,-47.608]],"c":false},"ix":2},"nm":"Path 1","mn":"ADBE Vector Shape - Group","hd":false,"_render":true},{"ty":"fl","c":{"a":0,"k":[1,1,1,1],"ix":4},"o":{"a":0,"k":100,"ix":5},"r":1,"bm":0,"nm":"Fill 1","mn":"ADBE Vector Graphic - Fill","hd":false,"_render":true},{"ty":"tr","p":{"a":0,"k":[397.959,255.082],"ix":2},"a":{"a":0,"k":[0,0],"ix":1},"s":{"a":0,"k":[100,100],"ix":3},"r":{"a":0,"k":0,"ix":6},"o":{"a":0,"k":100,"ix":7},"sk":{"a":0,"k":0,"ix":4},"sa":{"a":0,"k":0,"ix":5},"nm":"Transform","_render":true}],"nm":"Group 1","np":2,"cix":2,"bm":0,"ix":1,"mn":"ADBE Vector Group","hd":false,"_render":true},{"ty":"gr","it":[{"ty":"gr","it":[{"ty":"gr","it":[{"ty":"gr","it":[{"ind":0,"ty":"sh","ix":1,"ks":{"a":0,"k":{"i":[[0.08,-6.559],[0.037,2.375]],"o":[[-0.251,-2.968],[0.037,6.559]],"v":[[0.08,-6.559],[0.037,6.559]],"c":false},"ix":2},"nm":"Path 1","mn":"ADBE Vector Shape - Group","hd":false,"_render":true},{"ty":"st","c":{"a":0,"k":[0.5294,0.0941,0.2667,1],"ix":3},"o":{"a":0,"k":100,"ix":4},"w":{"a":0,"k":0.5,"ix":5},"lc":1,"lj":1,"ml":10,"bm":0,"nm":"Stroke 1","mn":"ADBE Vector Graphic - Stroke","hd":false,"_render":true},{"ty":"tr","p":{"a":0,"k":[473.824,285.963],"ix":2},"a":{"a":0,"k":[0,0],"ix":1},"s":{"a":0,"k":[100,100],"ix":3},"r":{"a":0,"k":0,"ix":6},"o":{"a":0,"k":100,"ix":7},"sk":{"a":0,"k":0,"ix":4},"sa":{"a":0,"k":0,"ix":5},"nm":"Transform","_render":true}],"nm":"Group 1","np":2,"cix":2,"bm":0,"ix":1,"mn":"ADBE Vector Group","hd":false,"_render":true},{"ty":"gr","it":[{"ind":0,"ty":"sh","ix":1,"ks":{"a":0,"k":{"i":[[-2.999,-17.188],[2.299,-5.902],[2.909,17.188]],"o":[[-2.999,-17.188],[3.195,2.466],[2.909,17.188]],"v":[[-2.999,-17.188],[2.747,-1.718],[2.909,17.188]],"c":false},"ix":2},"nm":"Path 1","mn":"ADBE Vector Shape - Group","hd":false,"_render":true},{"ty":"st","c":{"a":0,"k":[0.5294,0.0941,0.2667,1],"ix":3},"o":{"a":0,"k":100,"ix":4},"w":{"a":0,"k":0.5,"ix":5},"lc":1,"lj":1,"ml":10,"bm":0,"nm":"Stroke 1","mn":"ADBE Vector Graphic - Stroke","hd":false,"_render":true},{"ty":"tr","p":{"a":0,"k":[463.055,271.311],"ix":2},"a":{"a":0,"k":[0,0],"ix":1},"s":{"a":0,"k":[100,100],"ix":3},"r":{"a":0,"k":0,"ix":6},"o":{"a":0,"k":100,"ix":7},"sk":{"a":0,"k":0,"ix":4},"sa":{"a":0,"k":0,"ix":5},"nm":"Transform","_render":true}],"nm":"Group 2","np":2,"cix":2,"bm":0,"ix":2,"mn":"ADBE Vector Group","hd":false,"_render":true},{"ty":"gr","it":[{"ind":0,"ty":"sh","ix":1,"ks":{"a":0,"k":{"i":[[2.083,24.272],[3.133,9.23],[-2.252,-14.447999999999999]],"o":[[2.6100000000000003,16.798],[0.20399999999999996,-6.895],[-2.641,-24.272]],"v":[[2.083,24.272],[1.794,1.858],[-2.641,-24.272]],"c":false},"ix":2},"nm":"Path 1","mn":"ADBE Vector Shape - Group","hd":false,"_render":true},{"ty":"st","c":{"a":0,"k":[0.5294,0.0941,0.2667,1],"ix":3},"o":{"a":0,"k":100,"ix":4},"w":{"a":0,"k":0.5,"ix":5},"lc":1,"lj":1,"ml":10,"bm":0,"nm":"Stroke 1","mn":"ADBE Vector Graphic - Stroke","hd":false,"_render":true},{"ty":"tr","p":{"a":0,"k":[454.149,264.228],"ix":2},"a":{"a":0,"k":[0,0],"ix":1},"s":{"a":0,"k":[100,100],"ix":3},"r":{"a":0,"k":0,"ix":6},"o":{"a":0,"k":100,"ix":7},"sk":{"a":0,"k":0,"ix":4},"sa":{"a":0,"k":0,"ix":5},"nm":"Transform","_render":true}],"nm":"Group 3","np":2,"cix":2,"bm":0,"ix":3,"mn":"ADBE Vector Group","hd":false,"_render":true},{"ty":"gr","it":[{"ind":0,"ty":"sh","ix":1,"ks":{"a":0,"k":{"i":[[-6.002,74.417],[-8.286,39.699000000000005],[-26.953,24.844],[-33,-15.382000000000001],[-34.971000000000004,-29.316000000000003],[-24.85,-24.846],[-23.141,-3.813],[-18.54,-0.922],[-16.174,-27.212000000000003],[-19.197,-54.818],[-15.779,-74.668],[-8.418,-67.832],[-6.577,-68.358],[-0.005,-53.635],[0.3889999999999998,-59.945],[7.357000000000001,-57.315],[11.169,-43.775999999999996],[13.93,-27.081],[14.85,-39.568999999999996],[19.976999999999997,-45.61600000000001],[19.977,-21.034],[15.770000000000001,17.35],[34.036,74.417]],"o":[[-6.002,74.417],[-13.465,36.632000000000005],[-34.577,-0.395999999999999],[-34.05200000000001,-25.898],[-27.873,-28.79],[-22.22,-14.855999999999998],[-19.723,0.39300000000000024],[-18.54,-1.71],[-16.174,-38.518],[-17.883,-70.592],[-9.732,-74.142],[-8.418,-67.832],[-3.423,-61.786],[-0.005,-53.635],[5.911,-60.471],[9.461,-49.691],[13.009,-34.574],[13.93,-27.081],[16.69,-43.775],[21.817,-41.936],[19.977,-13.146],[18.924,31.022],[34.036,74.417]],"v":[[-6.002,74.417],[-12.696,37.087],[-30.765,12.224],[-33.526,-20.64],[-31.422,-29.053],[-23.535,-19.851],[-21.432,-1.71],[-18.54,-1.316],[-16.174,-32.865],[-18.54,-62.705],[-12.756,-74.405],[-8.418,-67.832],[-5,-65.072],[-0.005,-53.635],[3.15,-60.208],[8.409,-53.503],[12.089,-39.175],[13.93,-27.081],[15.77,-41.672],[20.897,-43.776],[19.977,-17.09],[17.347,24.186],[34.036,74.417]],"c":true},"ix":2},"nm":"Path 1","mn":"ADBE Vector Shape - Group","hd":false,"_render":true},{"ty":"fl","c":{"a":0,"k":[0.7272,0.5377,0.3928,1],"ix":4},"o":{"a":0,"k":100,"ix":5},"r":1,"bm":0,"nm":"Fill 1","mn":"ADBE Vector Graphic - Fill","hd":false,"_render":true},{"ty":"tr","p":{"a":0,"k":[459.888,308.273],"ix":2},"a":{"a":0,"k":[0,0],"ix":1},"s":{"a":0,"k":[100,100],"ix":3},"r":{"a":0,"k":0,"ix":6},"o":{"a":0,"k":100,"ix":7},"sk":{"a":0,"k":0,"ix":4},"sa":{"a":0,"k":0,"ix":5},"nm":"Transform","_render":true}],"nm":"Group 4","np":2,"cix":2,"bm":0,"ix":4,"mn":"ADBE Vector Group","hd":false,"_render":true},{"ty":"tr","p":{"a":0,"k":[459.888,308.273],"ix":2},"a":{"a":0,"k":[459.888,308.273],"ix":1},"s":{"a":0,"k":[100,100],"ix":3},"r":{"a":0,"k":0,"ix":6},"o":{"a":0,"k":100,"ix":7},"sk":{"a":0,"k":0,"ix":4},"sa":{"a":0,"k":0,"ix":5},"nm":"Transform","_render":true}],"nm":"Group 1","np":4,"cix":2,"bm":0,"ix":1,"mn":"ADBE Vector Group","hd":false,"_render":true},{"ty":"gr","it":[{"ind":0,"ty":"sh","ix":1,"ks":{"a":0,"k":{"i":[[-9.882,34.441],[-9.284,7.111],[-12.307,-14.841999999999999],[-8.889,-34.692],[-1.528,-27.856],[0.31299999999999994,-28.382],[6.885,-13.659],[12.325,10.827000000000002]],"o":[[-10.054,30.135],[-9.284,1.4580000000000002],[-10.993,-30.616],[-2.8419999999999996,-34.166000000000004],[-1.528,-27.856],[3.4669999999999996,-21.81],[6.885,-13.659],[11.692,34.441]],"v":[[-9.882,34.441],[-9.284,7.111],[-11.65,-22.729],[-5.866,-34.429],[-1.528,-27.856],[1.89,-25.096],[6.885,-13.659],[11.692,34.441]],"c":true},"ix":2},"nm":"Path 1","mn":"ADBE Vector Shape - Group","hd":false,"_render":true},{"ty":"fl","c":{"a":0,"k":[0.3333,0,0,1],"ix":4},"o":{"a":0,"k":100,"ix":5},"r":1,"bm":0,"nm":"Fill 1","mn":"ADBE Vector Graphic - Fill","hd":false,"_render":true},{"ty":"tr","p":{"a":0,"k":[449.313,268.297],"ix":2},"a":{"a":0,"k":[0,0],"ix":1},"s":{"a":0,"k":[100,100],"ix":3},"r":{"a":0,"k":0,"ix":6},"o":{"a":0,"k":40,"ix":7},"sk":{"a":0,"k":0,"ix":4},"sa":{"a":0,"k":0,"ix":5},"nm":"Transform","_render":true}],"nm":"Group 2","np":2,"cix":2,"bm":0,"ix":2,"mn":"ADBE Vector Group","hd":false,"_render":true},{"ty":"gr","it":[{"ind":0,"ty":"sh","ix":1,"ks":{"a":0,"k":{"i":[[-4.261,11.766],[-5.538,-3.339],[-6.984,-12.015],[3.137,-7.545],[6.049,11.766]],"o":[[-4.261,11.766],[-6.064,-8.597],[0.11399999999999988,-11.489],[4.452,-2.55],[6.049,11.766]],"v":[[-4.261,11.766],[-5.538,-3.339],[-3.435,-11.752],[4.452,-2.55],[6.049,11.766]],"c":false},"ix":2},"nm":"Path 1","mn":"ADBE Vector Shape - Group","hd":false,"_render":true},{"ty":"fl","c":{"a":0,"k":[0.3333,0,0,1],"ix":4},"o":{"a":0,"k":100,"ix":5},"r":1,"bm":0,"nm":"Fill 1","mn":"ADBE Vector Graphic - Fill","hd":false,"_render":true},{"ty":"tr","p":{"a":0,"k":[428.216,290.972],"ix":2},"a":{"a":0,"k":[0,0],"ix":1},"s":{"a":0,"k":[100,100],"ix":3},"r":{"a":0,"k":0,"ix":6},"o":{"a":0,"k":40,"ix":7},"sk":{"a":0,"k":0,"ix":4},"sa":{"a":0,"k":0,"ix":5},"nm":"Transform","_render":true}],"nm":"Group 3","np":2,"cix":2,"bm":0,"ix":3,"mn":"ADBE Vector Group","hd":false,"_render":true},{"ty":"gr","it":[{"ind":0,"ty":"sh","ix":1,"ks":{"a":0,"k":{"i":[[45.7,-47.618],[-43.335,-47.618],[-47.618,-45.701],[-47.618,-12.319],[-45.143,-10.536],[-40.497,-12.593],[-34.766,-15.588],[-15.75,-8.609],[-22.729,15.588],[-37.597,14.593],[-40.093,12.898],[-45.117000000000004,9.588],[-47.618,43.335],[-45.7,47.618],[43.335,47.618],[47.618,45.7],[47.618,-43.335]],"o":[[43.335,-47.618],[-45.7,-47.618],[-47.618,-43.335],[-47.022000000000006,-11.715000000000002],[-40.498,-12.609],[-37.924,-14.468],[-22.729,-15.588],[-15.75,8.609],[-34.584,15.588],[-40.093,12.895],[-40.093,12.898],[-47.618,12.613],[-47.618,45.7],[-43.335,47.618],[45.7,47.618],[47.618,43.335],[47.618,-45.701]],"v":[[43.335,-47.618],[-43.335,-47.618],[-47.618,-43.335],[-47.618,-12.319],[-40.498,-12.609],[-40.497,-12.593],[-31.338,-15.588],[-15.75,0],[-31.338,15.588],[-40.093,12.895],[-40.093,12.898],[-47.618,12.613],[-47.618,43.335],[-43.335,47.618],[43.335,47.618],[47.618,43.335],[47.618,-43.335]],"c":true},"ix":2},"nm":"Path 1","mn":"ADBE Vector Shape - Group","hd":false,"_render":true},{"ty":"fl","c":{"a":0,"k":[1,1,1,1],"ix":4},"o":{"a":0,"k":100,"ix":5},"r":1,"bm":0,"nm":"Fill 1","mn":"ADBE Vector Graphic - Fill","hd":false,"_render":true},{"ty":"tr","p":{"a":0,"k":[409.48,255.12],"ix":2},"a":{"a":0,"k":[0,0],"ix":1},"s":{"a":0,"k":[100,100],"ix":3},"r":{"a":0,"k":0,"ix":6},"o":{"a":0,"k":40,"ix":7},"sk":{"a":0,"k":0,"ix":4},"sa":{"a":0,"k":0,"ix":5},"nm":"Transform","_render":true}],"nm":"Group 4","np":2,"cix":2,"bm":0,"ix":4,"mn":"ADBE Vector Group","hd":false,"_render":true},{"ty":"gr","it":[{"ind":0,"ty":"sh","ix":1,"ks":{"a":0,"k":{"i":[[45.7,-47.618],[-43.335,-47.618],[-47.618,-45.701],[-47.618,-12.319],[-45.143,-10.536],[-40.497,-12.593],[-34.766,-15.588],[-15.75,-8.609],[-22.729,15.588],[-37.597,14.593],[-40.093,12.898],[-45.117000000000004,9.588],[-47.618,43.335],[-45.7,47.618],[43.335,47.618],[47.618,45.7],[47.618,-43.335]],"o":[[43.335,-47.618],[-45.7,-47.618],[-47.618,-43.335],[-47.022000000000006,-11.715000000000002],[-40.498,-12.609],[-37.924,-14.468],[-22.729,-15.588],[-15.75,8.609],[-34.584,15.588],[-40.093,12.895],[-40.093,12.898],[-47.618,12.613],[-47.618,45.7],[-43.335,47.618],[45.7,47.618],[47.618,43.335],[47.618,-45.701]],"v":[[43.335,-47.618],[-43.335,-47.618],[-47.618,-43.335],[-47.618,-12.319],[-40.498,-12.609],[-40.497,-12.593],[-31.338,-15.588],[-15.75,0],[-31.338,15.588],[-40.093,12.895],[-40.093,12.898],[-47.618,12.613],[-47.618,43.335],[-43.335,47.618],[43.335,47.618],[47.618,43.335],[47.618,-43.335]],"c":true},"ix":2},"nm":"Path 1","mn":"ADBE Vector Shape - Group","hd":false,"_render":true},{"ty":"fl","c":{"a":0,"k":[1,0.26,0.556,1],"ix":4},"o":{"a":0,"k":100,"ix":5},"r":1,"bm":0,"nm":"Fill 1","mn":"ADBE Vector Graphic - Fill","hd":false,"_render":true},{"ty":"tr","p":{"a":0,"k":[409.48,255.12],"ix":2},"a":{"a":0,"k":[0,0],"ix":1},"s":{"a":0,"k":[100,100],"ix":3},"r":{"a":0,"k":0,"ix":6},"o":{"a":0,"k":100,"ix":7},"sk":{"a":0,"k":0,"ix":4},"sa":{"a":0,"k":0,"ix":5},"nm":"Transform","_render":true}],"nm":"Group 5","np":2,"cix":2,"bm":0,"ix":5,"mn":"ADBE Vector Group","hd":false,"_render":true},{"ty":"tr","p":{"a":0,"k":[409.48,255.12],"ix":2},"a":{"a":0,"k":[409.48,255.12],"ix":1},"s":{"a":0,"k":[100,100],"ix":3},"r":{"a":0,"k":0,"ix":6},"o":{"a":0,"k":100,"ix":7},"sk":{"a":0,"k":0,"ix":4},"sa":{"a":0,"k":0,"ix":5},"nm":"Transform","_render":true}],"nm":"Group 1","np":5,"cix":2,"bm":0,"ix":1,"mn":"ADBE Vector Group","hd":false,"_render":true},{"ty":"tr","p":{"a":0,"k":[409.48,255.12],"ix":2},"a":{"a":0,"k":[409.48,255.12],"ix":1},"s":{"a":0,"k":[100,100],"ix":3},"r":{"a":0,"k":0,"ix":6},"o":{"a":0,"k":100,"ix":7},"sk":{"a":0,"k":0,"ix":4},"sa":{"a":0,"k":0,"ix":5},"nm":"Transform","_render":true}],"nm":"Group 2","np":1,"cix":2,"bm":0,"ix":2,"mn":"ADBE Vector Group","hd":false,"_render":true}],"ip":0,"op":120,"st":0,"bm":0,"completed":true},{"ddd":0,"ind":2,"ty":4,"nm":"Hand 3","sr":1,"ks":{"o":{"a":1,"k":[{"i":{"x":[0.19],"y":[1]},"o":{"x":[0.333],"y":[0]},"t":10,"s":[0]},{"t":30,"s":[100]}],"ix":11},"r":{"a":0,"k":0,"ix":10},"p":{"a":1,"k":[{"i":{"x":0.19,"y":1},"o":{"x":0.333,"y":0},"t":10,"s":[396.638,2.094,0],"to":null,"ti":null},{"i":{"x":0.19,"y":0.19},"o":{"x":0.333,"y":0.333},"t":30,"s":[396.638,102.094,0],"to":null,"ti":null},{"i":{"x":0.19,"y":1},"o":{"x":0.333,"y":0},"t":55,"s":[396.638,102.094,0],"to":null,"ti":null},{"t":70,"s":[394.138,102.094,0]}],"ix":2},"a":{"a":0,"k":[396.638,102.094,0],"ix":1},"s":{"a":0,"k":[100,100,100],"ix":6}},"ao":0,"shapes":[{"ty":"gr","it":[{"ty":"gr","it":[{"ind":0,"ty":"sh","ix":1,"ks":{"a":0,"k":{"i":[[-2.026,2.284],[1.0879999999999999,-0.45299999999999985]],"o":[[-0.32099999999999973,1.134],[2.026,-2.284]],"v":[[-2.026,2.284],[2.026,-2.284]],"c":false},"ix":2},"nm":"Path 1","mn":"ADBE Vector Shape - Group","hd":false,"_render":true},{"ty":"st","c":{"a":0,"k":[0.993,0.6043,0.307,1],"ix":3},"o":{"a":0,"k":100,"ix":4},"w":{"a":0,"k":1,"ix":5},"lc":2,"lj":2,"bm":0,"nm":"Stroke 1","mn":"ADBE Vector Graphic - Stroke","hd":false,"_render":true},{"ty":"tr","p":{"a":0,"k":[309.091,203.753],"ix":2},"a":{"a":0,"k":[0,0],"ix":1},"s":{"a":0,"k":[100,100],"ix":3},"r":{"a":0,"k":0,"ix":6},"o":{"a":0,"k":100,"ix":7},"sk":{"a":0,"k":0,"ix":4},"sa":{"a":0,"k":0,"ix":5},"nm":"Transform","_render":true}],"nm":"Group 1","np":2,"cix":2,"bm":0,"ix":1,"mn":"ADBE Vector Group","hd":false,"_render":true},{"ty":"gr","it":[{"ind":0,"ty":"sh","ix":1,"ks":{"a":0,"k":{"i":[[3.175,17.081],[-2.5730000000000004,7.670999999999999],[1.2840000000000003,-12.261]],"o":[[0.33099999999999996,13.712],[-5.099,-0.22199999999999998],[4.171,-17.081]],"v":[[3.175,17.081],[-4.057,3.033],[4.171,-17.081]],"c":false},"ix":2},"nm":"Path 1","mn":"ADBE Vector Shape - Group","hd":false,"_render":true},{"ty":"st","c":{"a":0,"k":[0.993,0.6043,0.307,1],"ix":3},"o":{"a":0,"k":100,"ix":4},"w":{"a":0,"k":1,"ix":5},"lc":2,"lj":2,"bm":0,"nm":"Stroke 1","mn":"ADBE Vector Graphic - Stroke","hd":false,"_render":true},{"ty":"tr","p":{"a":0,"k":[273.534,205.96],"ix":2},"a":{"a":0,"k":[0,0],"ix":1},"s":{"a":0,"k":[100,100],"ix":3},"r":{"a":0,"k":0,"ix":6},"o":{"a":0,"k":100,"ix":7},"sk":{"a":0,"k":0,"ix":4},"sa":{"a":0,"k":0,"ix":5},"nm":"Transform","_render":true}],"nm":"Group 2","np":2,"cix":2,"bm":0,"ix":2,"mn":"ADBE Vector Group","hd":false,"_render":true},{"ty":"gr","it":[{"ind":0,"ty":"sh","ix":1,"ks":{"a":0,"k":{"i":[[6.39,17.878],[2.394,14.199000000000002],[-3.142,7.304],[-7.069,-0.726],[1.864,-17.878]],"o":[[3.7809999999999997,15.766],[-1.482,9.614],[-6.103,2.386],[-4.575,-6.521],[1.864,-17.878]],"v":[[6.39,17.878],[0,11.367],[-4.476,5.088],[-5.822,-3.624],[1.864,-17.878]],"c":false},"ix":2},"nm":"Path 1","mn":"ADBE Vector Shape - Group","hd":false,"_render":true},{"ty":"st","c":{"a":0,"k":[0.993,0.6043,0.307,1],"ix":3},"o":{"a":0,"k":100,"ix":4},"w":{"a":0,"k":1,"ix":5},"lc":2,"lj":2,"bm":0,"nm":"Stroke 1","mn":"ADBE Vector Graphic - Stroke","hd":false,"_render":true},{"ty":"tr","p":{"a":0,"k":[285.214,210.141],"ix":2},"a":{"a":0,"k":[0,0],"ix":1},"s":{"a":0,"k":[100,100],"ix":3},"r":{"a":0,"k":0,"ix":6},"o":{"a":0,"k":100,"ix":7},"sk":{"a":0,"k":0,"ix":4},"sa":{"a":0,"k":0,"ix":5},"nm":"Transform","_render":true}],"nm":"Group 3","np":2,"cix":2,"bm":0,"ix":3,"mn":"ADBE Vector Group","hd":false,"_render":true},{"ty":"gr","it":[{"ind":0,"ty":"sh","ix":1,"ks":{"a":0,"k":{"i":[[4.871,12.323],[1.045,9.887],[-4.578,2.922],[-0.5349999999999999,-9.401]],"o":[[2.9670000000000005,11.112],[-2.137,6.685],[-5.303000000000001,-3.3089999999999997],[1.31,-12.323]],"v":[[4.871,12.323],[-0.546,8.286],[-4.839,0.68],[1.31,-12.323]],"c":false},"ix":2},"nm":"Path 1","mn":"ADBE Vector Shape - Group","hd":false,"_render":true},{"ty":"st","c":{"a":0,"k":[0.993,0.6043,0.307,1],"ix":3},"o":{"a":0,"k":100,"ix":4},"w":{"a":0,"k":1,"ix":5},"lc":2,"lj":2,"bm":0,"nm":"Stroke 1","mn":"ADBE Vector Graphic - Stroke","hd":false,"_render":true},{"ty":"tr","p":{"a":0,"k":[295.232,211.885],"ix":2},"a":{"a":0,"k":[0,0],"ix":1},"s":{"a":0,"k":[100,100],"ix":3},"r":{"a":0,"k":0,"ix":6},"o":{"a":0,"k":100,"ix":7},"sk":{"a":0,"k":0,"ix":4},"sa":{"a":0,"k":0,"ix":5},"nm":"Transform","_render":true}],"nm":"Group 4","np":2,"cix":2,"bm":0,"ix":4,"mn":"ADBE Vector Group","hd":false,"_render":true},{"ty":"gr","it":[{"ind":0,"ty":"sh","ix":1,"ks":{"a":0,"k":{"i":[[-0.79,8.522],[-40.211999999999996,3.573],[-66.889,30.566000000000003],[-61.326,60.22],[-55.738,62.408],[-53.859,50.693],[-44.847,67.945],[-32.239,64.974],[-26.565,58.16],[-20.385,59.963],[-24.248,45.801],[-19.613,38.849],[4.723999999999999,43.139],[16.178,33.441],[67.154,-63.074],[24.425,-63.074]],"o":[[-1.82,9.037],[-54.632,10.783],[-67.404,42.926],[-60.811,62.28],[-54.117000000000004,54.299],[-53.859,50.693],[-36.35,60.22],[-25.793,59.448],[-26.565,58.16],[-19.87,49.663000000000004],[-24.248,45.801],[-19.613,38.849],[16.112,35.247],[16.178,33.441],[67.154,-63.074],[24.425,-63.074]],"v":[[-0.79,8.522],[-47.422,7.178],[-67.146,36.746],[-61.069,61.25],[-54.374,55.586],[-53.859,50.693],[-36.35,60.22],[-29.016,62.211],[-26.565,58.16],[-20.128,54.813],[-24.248,45.801],[-19.613,38.849],[11.286,38.591],[16.178,33.441],[67.154,-63.074],[24.425,-63.074]],"c":true},"ix":2},"nm":"Path 1","mn":"ADBE Vector Shape - Group","hd":false,"_render":true},{"ty":"fl","c":{"a":0,"k":[0.9916,0.6838,0.4484,1],"ix":4},"o":{"a":0,"k":100,"ix":5},"r":1,"bm":0,"nm":"Fill 1","mn":"ADBE Vector Graphic - Fill","hd":false,"_render":true},{"ty":"tr","p":{"a":0,"k":[326.796,166.702],"ix":2},"a":{"a":0,"k":[0,0],"ix":1},"s":{"a":0,"k":[100,100],"ix":3},"r":{"a":0,"k":0,"ix":6},"o":{"a":0,"k":100,"ix":7},"sk":{"a":0,"k":0,"ix":4},"sa":{"a":0,"k":0,"ix":5},"nm":"Transform","_render":true}],"nm":"Group 5","np":2,"cix":2,"bm":0,"ix":5,"mn":"ADBE Vector Group","hd":false,"_render":true},{"ty":"gr","it":[{"ind":0,"ty":"sh","ix":1,"ks":{"a":0,"k":{"i":[[-21.037,7.884],[-17.233999999999998,11.068999999999999],[-5.859,13.618],[9.053,14.024000000000001],[14.435,7.569],[20.738,8.42],[19.076999999999998,-6.2589999999999995],[18.317,-12.192],[-22.257,-11.718]],"o":[[-21.037,7.884],[-14.103,7.569],[-0.865,11.112],[12.967,10.285],[14.435,7.569],[22.942,-0.6659999999999999],[16.744,-8.565],[17.612,-12.192],[-22.257,-11.718]],"v":[[-21.037,7.884],[-14.103,7.569],[-0.865,11.112],[12.967,10.285],[14.435,7.569],[22.152,2.591],[16.744,-8.565],[18.101,-12.192],[-22.257,-11.718]],"c":true},"ix":2},"nm":"Path 1","mn":"ADBE Vector Shape - Group","hd":false,"_render":true},{"ty":"fl","c":{"a":0,"k":[0.3333,0,0,1],"ix":4},"o":{"a":0,"k":100,"ix":5},"r":1,"bm":0,"nm":"Fill 1","mn":"ADBE Vector Graphic - Fill","hd":false,"_render":true},{"ty":"tr","p":{"a":0,"k":[288.965,220.45],"ix":2},"a":{"a":0,"k":[0,0],"ix":1},"s":{"a":0,"k":[100,100],"ix":3},"r":{"a":0,"k":0,"ix":6},"o":{"a":0,"k":40,"ix":7},"sk":{"a":0,"k":0,"ix":4},"sa":{"a":0,"k":0,"ix":5},"nm":"Transform","_render":true}],"nm":"Group 6","np":2,"cix":2,"bm":0,"ix":6,"mn":"ADBE Vector Group","hd":false,"_render":true},{"ty":"tr","p":{"a":0,"k":[288.965,220.45],"ix":2},"a":{"a":0,"k":[288.965,220.45],"ix":1},"s":{"a":0,"k":[100,100],"ix":3},"r":{"a":0,"k":0,"ix":6},"o":{"a":0,"k":100,"ix":7},"sk":{"a":0,"k":0,"ix":4},"sa":{"a":0,"k":0,"ix":5},"nm":"Transform","_render":true}],"nm":"Group 1","np":6,"cix":2,"bm":0,"ix":1,"mn":"ADBE Vector Group","hd":false,"_render":true},{"ty":"gr","it":[{"ind":0,"ty":"sh","ix":1,"ks":{"a":0,"k":{"i":[[-10.99,13.364],[-10.99,4.558],[10.99,-13.364],[10.99,-6.452],[0.019999999999999796,-2.3289999999999997],[0,13.364]],"o":[[-10.99,13.364],[9.42,-12.629999999999999],[10.99,-13.364],[10.99,-6.452],[-3.74,8.855],[0,13.364]],"v":[[-10.99,13.364],[-0.785,-4.036],[10.99,-13.364],[10.99,-6.452],[-1.86,3.263],[0,13.364]],"c":true},"ix":2},"nm":"Path 1","mn":"ADBE Vector Shape - Group","hd":false,"_render":true},{"ty":"fl","c":{"a":0,"k":[1,1,1,1],"ix":4},"o":{"a":0,"k":100,"ix":5},"r":1,"bm":0,"nm":"Fill 1","mn":"ADBE Vector Graphic - Fill","hd":false,"_render":true},{"ty":"tr","p":{"a":0,"k":[341.573,289.136],"ix":2},"a":{"a":0,"k":[0,0],"ix":1},"s":{"a":0,"k":[100,100],"ix":3},"r":{"a":0,"k":0,"ix":6},"o":{"a":0,"k":100,"ix":7},"sk":{"a":0,"k":0,"ix":4},"sa":{"a":0,"k":0,"ix":5},"nm":"Transform","_render":true}],"nm":"Group 2","np":2,"cix":2,"bm":0,"ix":2,"mn":"ADBE Vector Group","hd":false,"_render":true},{"ty":"gr","it":[{"ind":0,"ty":"sh","ix":1,"ks":{"a":0,"k":{"i":[[-26.38,47.512],[-23.31,31.268],[0.584,-47.532],[8.493,-47.532],[27.244999999999997,-28.118],[-3.346,15.375],[-14.104,47.532]],"o":[[-26.38,47.512],[29.138,0.9420000000000002],[0.584,-47.532],[8.493,-47.532],[25.366,30.756],[-20.8,46.137],[-14.104,47.532]],"v":[[-26.38,47.512],[2.914,16.105],[0.584,-47.532],[8.493,-47.532],[26.348,0],[-12.073,30.756],[-14.104,47.532]],"c":true},"ix":2},"nm":"Path 1","mn":"ADBE Vector Shape - Group","hd":false,"_render":true},{"ty":"fl","c":{"a":0,"k":[1,1,1,1],"ix":4},"o":{"a":0,"k":100,"ix":5},"r":1,"bm":0,"nm":"Fill 1","mn":"ADBE Vector Graphic - Fill","hd":false,"_render":true},{"ty":"tr","p":{"a":0,"k":[300.417,254.968],"ix":2},"a":{"a":0,"k":[0,0],"ix":1},"s":{"a":0,"k":[100,100],"ix":3},"r":{"a":0,"k":0,"ix":6},"o":{"a":0,"k":100,"ix":7},"sk":{"a":0,"k":0,"ix":4},"sa":{"a":0,"k":0,"ix":5},"nm":"Transform","_render":true}],"nm":"Group 3","np":2,"cix":2,"bm":0,"ix":3,"mn":"ADBE Vector Group","hd":false,"_render":true},{"ty":"gr","it":[{"ind":0,"ty":"sh","ix":1,"ks":{"a":0,"k":{"i":[[56.549,-31.534],[41.353,-30.414],[38.78,-28.555],[32.359,-27.599],[31.709,-59.281],[29.790999999999997,-63.564],[-59.244,-63.564],[-63.527,-61.647],[-63.527,-28.265],[-61.05199999999999,-26.482],[-56.406,-28.539],[-50.675,-31.534],[-31.659,-24.555],[-38.638,-0.358],[-53.506,-1.3519999999999999],[-56.002,-3.048],[-61.026,-6.3580000000000005],[-63.527,27.39],[-61.609,31.673],[-21.83,31.673],[-22.114,39.221],[-22.113,39.221],[-24.804,44.730999999999995],[-17.825,63.564],[6.372,56.586],[5.265,41.388000000000005],[3.393,38.816],[2.53,32.244],[27.426,31.673],[31.709,29.756],[31.709,-3.394],[39.184,-3.048],[39.184,-3.05],[44.693999999999996,-0.358],[63.527,-7.337]],"o":[[44.512,-31.534],[38.78,-28.539],[34.264,-26.54],[31.709,-28.214],[31.709,-61.647],[27.426,-63.564],[-61.609,-63.564],[-63.527,-59.281],[-62.931000000000004,-27.661],[-56.407,-28.555],[-53.833,-30.414],[-38.638,-31.534],[-31.659,-7.337],[-50.493,-0.358],[-56.002,-3.05],[-56.002,-3.048],[-63.527,-3.333],[-63.527,29.756],[-59.244,31.673],[-18.770999999999997,34.168],[-22.114,39.221],[-23.811,41.717],[-24.804,56.586],[-0.6069999999999993,63.564],[6.372,44.553],[3.393,38.816],[1.2939999999999996,34.113],[3.126,31.673],[29.790999999999997,31.673],[31.709,27.39],[34.226,-6.314],[39.184,-3.048],[41.68,-1.3519999999999999],[56.549,-0.358],[63.527,-24.555]],"v":[[47.94,-31.534],[38.78,-28.539],[38.78,-28.555],[31.709,-28.214],[31.709,-59.281],[27.426,-63.564],[-59.244,-63.564],[-63.527,-59.281],[-63.527,-28.265],[-56.407,-28.555],[-56.406,-28.539],[-47.247,-31.534],[-31.659,-15.946],[-47.247,-0.358],[-56.002,-3.05],[-56.002,-3.048],[-63.527,-3.333],[-63.527,27.39],[-59.244,31.673],[-21.83,31.673],[-22.114,39.221],[-22.113,39.221],[-24.804,47.977],[-9.216,63.564],[6.372,47.977],[3.393,38.816],[3.393,38.816],[3.126,31.673],[27.426,31.673],[31.709,27.39],[31.709,-3.394],[39.184,-3.048],[39.184,-3.05],[47.94,-0.358],[63.527,-15.946]],"c":true},"ix":2},"nm":"Path 1","mn":"ADBE Vector Shape - Group","hd":false,"_render":true},{"ty":"fl","c":{"a":0,"k":[1,0.26,0.556,1],"ix":4},"o":{"a":0,"k":100,"ix":5},"r":1,"bm":0,"nm":"Fill 1","mn":"ADBE Vector Graphic - Fill","hd":false,"_render":true},{"ty":"tr","p":{"a":0,"k":[320.853,270.994],"ix":2},"a":{"a":0,"k":[0,0],"ix":1},"s":{"a":0,"k":[100,100],"ix":3},"r":{"a":0,"k":0,"ix":6},"o":{"a":0,"k":100,"ix":7},"sk":{"a":0,"k":0,"ix":4},"sa":{"a":0,"k":0,"ix":5},"nm":"Transform","_render":true}],"nm":"Group 4","np":2,"cix":2,"bm":0,"ix":4,"mn":"ADBE Vector Group","hd":false,"_render":true}],"ip":0,"op":120,"st":0,"bm":0,"completed":true},{"ddd":0,"ind":3,"ty":4,"nm":"Hand 2","sr":1,"ks":{"o":{"a":1,"k":[{"i":{"x":[0.19],"y":[1]},"o":{"x":[0.333],"y":[0]},"t":13,"s":[0]},{"t":33,"s":[100]}],"ix":11},"r":{"a":0,"k":0,"ix":10},"p":{"a":1,"k":[{"i":{"x":0.19,"y":1},"o":{"x":0.333,"y":0},"t":13,"s":[125.284,487.346,0],"to":null,"ti":null},{"i":{"x":0.19,"y":0.19},"o":{"x":0.333,"y":0.333},"t":33,"s":[125.284,387.346,0],"to":null,"ti":null},{"i":{"x":0.19,"y":1},"o":{"x":0.333,"y":0},"t":55,"s":[125.284,387.346,0],"to":null,"ti":null},{"t":70,"s":[127.784,387.346,0]}],"ix":2},"a":{"a":0,"k":[125.284,387.346,0],"ix":1},"s":{"a":0,"k":[100,100,100],"ix":6}},"ao":0,"shapes":[{"ty":"gr","it":[{"ty":"gr","it":[{"ind":0,"ty":"sh","ix":1,"ks":{"a":0,"k":{"i":[[-9.676,19.75],[-4.321,15.163],[8.727,-16.438]],"o":[[-6.902,18.777],[-1.5410000000000001,9.980999999999998],[9.676,-19.75]],"v":[[-9.676,19.75],[-2.931,12.572],[9.676,-19.75]],"c":false},"ix":2},"nm":"Path 1","mn":"ADBE Vector Shape - Group","hd":false,"_render":true},{"ty":"st","c":{"a":0,"k":[1,0.5569,0.2275,1],"ix":3},"o":{"a":0,"k":100,"ix":4},"w":{"a":0,"k":0.75,"ix":5},"lc":2,"lj":2,"bm":0,"nm":"Stroke 1","mn":"ADBE Vector Graphic - Stroke","hd":false,"_render":true},{"ty":"tr","p":{"a":0,"k":[233.562,295.756],"ix":2},"a":{"a":0,"k":[0,0],"ix":1},"s":{"a":0,"k":[100,100],"ix":3},"r":{"a":0,"k":0,"ix":6},"o":{"a":0,"k":100,"ix":7},"sk":{"a":0,"k":0,"ix":4},"sa":{"a":0,"k":0,"ix":5},"nm":"Transform","_render":true}],"nm":"Group 1","np":2,"cix":2,"bm":0,"ix":1,"mn":"ADBE Vector Group","hd":false,"_render":true},{"ty":"gr","it":[{"ind":0,"ty":"sh","ix":1,"ks":{"a":0,"k":{"i":[[-5.492,18.772],[-0.5170000000000001,17.902],[5.492,-18.772]],"o":[[-2.506,18.485],[3.622,14.450000000000001],[5.492,-18.772]],"v":[[-5.492,18.772],[0.968,16.664],[5.492,-18.772]],"c":false},"ix":2},"nm":"Path 1","mn":"ADBE Vector Shape - Group","hd":false,"_render":true},{"ty":"st","c":{"a":0,"k":[1,0.5569,0.2275,1],"ix":3},"o":{"a":0,"k":100,"ix":4},"w":{"a":0,"k":0.75,"ix":5},"lc":2,"lj":2,"bm":0,"nm":"Stroke 1","mn":"ADBE Vector Graphic - Stroke","hd":false,"_render":true},{"ty":"tr","p":{"a":0,"k":[202.15,295.921],"ix":2},"a":{"a":0,"k":[0,0],"ix":1},"s":{"a":0,"k":[100,100],"ix":3},"r":{"a":0,"k":0,"ix":6},"o":{"a":0,"k":100,"ix":7},"sk":{"a":0,"k":0,"ix":4},"sa":{"a":0,"k":0,"ix":5},"nm":"Transform","_render":true}],"nm":"Group 2","np":2,"cix":2,"bm":0,"ix":2,"mn":"ADBE Vector Group","hd":false,"_render":true},{"ty":"gr","it":[{"ind":0,"ty":"sh","ix":1,"ks":{"a":0,"k":{"i":[[-6.43,20.344],[2.602,3.6839999999999975]],"o":[[-2.098,16.636000000000003],[6.43,-20.344]],"v":[[-6.43,20.344],[6.43,-20.344]],"c":false},"ix":2},"nm":"Path 1","mn":"ADBE Vector Shape - Group","hd":false,"_render":true},{"ty":"st","c":{"a":0,"k":[1,0.5569,0.2275,1],"ix":3},"o":{"a":0,"k":100,"ix":4},"w":{"a":0,"k":0.75,"ix":5},"lc":2,"lj":2,"bm":0,"nm":"Stroke 1","mn":"ADBE Vector Graphic - Stroke","hd":false,"_render":true},{"ty":"tr","p":{"a":0,"k":[223.209,296.304],"ix":2},"a":{"a":0,"k":[0,0],"ix":1},"s":{"a":0,"k":[100,100],"ix":3},"r":{"a":0,"k":0,"ix":6},"o":{"a":0,"k":100,"ix":7},"sk":{"a":0,"k":0,"ix":4},"sa":{"a":0,"k":0,"ix":5},"nm":"Transform","_render":true}],"nm":"Group 3","np":2,"cix":2,"bm":0,"ix":3,"mn":"ADBE Vector Group","hd":false,"_render":true},{"ty":"gr","it":[{"ind":0,"ty":"sh","ix":1,"ks":{"a":0,"k":{"i":[[-15.773,5.208],[-11.618,8.86],[3.825,1.574],[17.236,-4.491999999999999],[2.9999999999999996,-6.204000000000001],[-9.618,-2.157]],"o":[[-15.422,5.501],[-1.9800000000000004,4.884],[16.673000000000002,-4.246],[9.318,-8.846],[-5.571999999999999,-3.362],[-9.618,-2.157]],"v":[[-15.773,5.208],[-6.799,6.872],[10.249,-1.336],[13.277,-6.669],[-1.286,-4.783],[-9.618,-2.157]],"c":true},"ix":2},"nm":"Path 1","mn":"ADBE Vector Shape - Group","hd":false,"_render":true},{"ty":"fl","c":{"a":0,"k":[0.991,0.6612,0.409,1],"ix":4},"o":{"a":0,"k":100,"ix":5},"r":1,"bm":0,"nm":"Fill 1","mn":"ADBE Vector Graphic - Fill","hd":false,"_render":true},{"ty":"tr","p":{"a":0,"k":[238.784,308.493],"ix":2},"a":{"a":0,"k":[0,0],"ix":1},"s":{"a":0,"k":[100,100],"ix":3},"r":{"a":0,"k":0,"ix":6},"o":{"a":0,"k":100,"ix":7},"sk":{"a":0,"k":0,"ix":4},"sa":{"a":0,"k":0,"ix":5},"nm":"Transform","_render":true}],"nm":"Group 4","np":2,"cix":2,"bm":0,"ix":4,"mn":"ADBE Vector Group","hd":false,"_render":true},{"ty":"gr","it":[{"ind":0,"ty":"sh","ix":1,"ks":{"a":0,"k":{"i":[[-21.834,55.6],[-9.121,0.543],[11.654,-5.596],[32.906,-13.129],[41.388999999999996,-12.45],[59.465,-53.655],[57.131,-56.439],[41.592,-31.8],[45.79,-50.41],[39.45,-56.022],[28.446,-27.84],[24.384,-22.969],[23.879,-49.567],[18.233,-55.007999999999996],[10.143,-29.807],[-16.549,-31.133],[-59.465,55.6]],"o":[[-21.753,53.781],[-1.9940000000000007,-6.258],[33.195,-8.66],[32.906,-13.129],[47.028,-20.631999999999998],[59.465,-53.655],[45.557,-45.318999999999996],[41.592,-31.8],[45.943999999999996,-56.994],[35.324,-45.27],[26.619,-24.933],[21.446,-22.626],[23.861,-55.457],[13.413,-44.426],[10.143,-29.807],[-29.973000000000003,-22.526],[-59.465,55.6]],"v":[[-21.834,55.6],[-9.121,0.543],[18.028,-6.503],[32.906,-13.129],[45.105,-17.842],[59.465,-53.655],[51.344,-50.879],[41.592,-31.8],[45.867,-53.702],[37.387,-50.646],[28.446,-27.84],[21.446,-22.626],[23.87,-52.512],[15.823,-49.717],[10.143,-29.807],[-21.138,-28.191],[-59.465,55.6]],"c":true},"ix":2},"nm":"Path 1","mn":"ADBE Vector Shape - Group","hd":false,"_render":true},{"ty":"fl","c":{"a":0,"k":[0.991,0.6612,0.409,1],"ix":4},"o":{"a":0,"k":100,"ix":5},"r":1,"bm":0,"nm":"Fill 1","mn":"ADBE Vector Graphic - Fill","hd":false,"_render":true},{"ty":"tr","p":{"a":0,"k":[183.773,329.662],"ix":2},"a":{"a":0,"k":[0,0],"ix":1},"s":{"a":0,"k":[100,100],"ix":3},"r":{"a":0,"k":0,"ix":6},"o":{"a":0,"k":100,"ix":7},"sk":{"a":0,"k":0,"ix":4},"sa":{"a":0,"k":0,"ix":5},"nm":"Transform","_render":true}],"nm":"Group 5","np":2,"cix":2,"bm":0,"ix":5,"mn":"ADBE Vector Group","hd":false,"_render":true},{"ty":"tr","p":{"a":0,"k":[183.773,329.662],"ix":2},"a":{"a":0,"k":[183.773,329.662],"ix":1},"s":{"a":0,"k":[100,100],"ix":3},"r":{"a":0,"k":0,"ix":6},"o":{"a":0,"k":100,"ix":7},"sk":{"a":0,"k":0,"ix":4},"sa":{"a":0,"k":0,"ix":5},"nm":"Transform","_render":true}],"nm":"Group 1","np":5,"cix":2,"bm":0,"ix":1,"mn":"ADBE Vector Group","hd":false,"_render":true},{"ty":"gr","it":[{"ind":0,"ty":"sh","ix":1,"ks":{"a":0,"k":{"i":[[36.281,-39.512],[36.799,-38.245],[34.784,-26.193],[12.309999999999999,-14.393],[-10.232,2.208],[-13.528,16.444000000000003],[-22.307,27.894000000000002],[-39.868,30.318],[-45.654,39.509],[-31.293,37.13],[-14.846,30.468],[-11.017000000000001,19.641],[-4.6080000000000005,-0.08800000000000008],[25.677,-9.059999999999999],[45.873,-33.82299999999999]],"o":[[36.717999999999996,-38.978],[37.049,-31.901999999999997],[23.525,-15.152000000000001],[-4.341,-5.335999999999999],[-13.17,13.549],[-16.999,24.376],[-33.446,31.038],[-45.654,30.207],[-39.868,39.62],[-20.154,33.986],[-11.375,22.536],[-8.079,8.300999999999998],[12.042,-9.145],[36.936,-20.101],[45.65,-39.477]],"v":[[36.281,-39.512],[36.826,-37.556],[30.744,-22.231],[3.428,-9.562],[-12.45,10.77],[-14.679,19.074],[-27.877,29.466],[-45.654,30.207],[-45.654,39.509],[-25.724,35.558],[-12.526,25.166],[-10.297,16.862],[3.161,-4.314],[32.896,-16.139],[45.65,-39.477]],"c":true},"ix":2},"nm":"Path 1","mn":"ADBE Vector Shape - Group","hd":false,"_render":true},{"ty":"fl","c":{"a":0,"k":[1,1,1,1],"ix":4},"o":{"a":0,"k":100,"ix":5},"r":1,"bm":0,"nm":"Fill 1","mn":"ADBE Vector Graphic - Fill","hd":false,"_render":true},{"ty":"tr","p":{"a":0,"k":[203.001,246.942],"ix":2},"a":{"a":0,"k":[0,0],"ix":1},"s":{"a":0,"k":[100,100],"ix":3},"r":{"a":0,"k":0,"ix":6},"o":{"a":0,"k":100,"ix":7},"sk":{"a":0,"k":0,"ix":4},"sa":{"a":0,"k":0,"ix":5},"nm":"Transform","_render":true}],"nm":"Group 2","np":2,"cix":2,"bm":0,"ix":2,"mn":"ADBE Vector Group","hd":false,"_render":true},{"ty":"gr","it":[{"ind":0,"ty":"sh","ix":1,"ks":{"a":0,"k":{"i":[[-34.958,5.659],[-21.865,3.315],[-13.09,2.815],[-11.887,-16.904],[-5.452,10.61],[5.928,8.323],[9.74,-14.328],[21.517,-9.812],[26.851999999999997,-18.423],[34.958,-18.404],[25.679,9.039],[3.682,18.404],[-15.584,17.157]],"o":[[-34.958,5.659],[-15.584,2.815],[-13.09,2.815],[-1.81,-17.645],[-5.452,10.61],[5.928,8.323],[18.201,-17.214],[21.517,-9.812],[34.958,-18.404],[34.958,-18.404],[25.679,9.039],[3.682,18.404],[-15.584,17.157]],"v":[[-34.958,5.659],[-15.584,2.815],[-13.09,2.815],[-1.81,-17.645],[-5.452,10.61],[5.928,8.323],[18.201,-17.214],[21.517,-9.812],[34.958,-18.404],[34.958,-18.404],[25.679,9.039],[3.682,18.404],[-15.584,17.157]],"c":true},"ix":2},"nm":"Path 1","mn":"ADBE Vector Shape - Group","hd":false,"_render":true},{"ty":"fl","c":{"a":0,"k":[0.3333,0,0,1],"ix":4},"o":{"a":0,"k":100,"ix":5},"r":1,"bm":0,"nm":"Fill 1","mn":"ADBE Vector Graphic - Fill","hd":false,"_render":true},{"ty":"tr","p":{"a":0,"k":[203.96,294.364],"ix":2},"a":{"a":0,"k":[0,0],"ix":1},"s":{"a":0,"k":[100,100],"ix":3},"r":{"a":0,"k":0,"ix":6},"o":{"a":0,"k":40,"ix":7},"sk":{"a":0,"k":0,"ix":4},"sa":{"a":0,"k":0,"ix":5},"nm":"Transform","_render":true}],"nm":"Group 3","np":2,"cix":2,"bm":0,"ix":3,"mn":"ADBE Vector Group","hd":false,"_render":true},{"ty":"gr","it":[{"ind":0,"ty":"sh","ix":1,"ks":{"a":0,"k":{"i":[[72.064,-15.588],[56.868,-14.468],[54.295,-12.609],[48.13,-11.531],[47.366,-43.335],[45.448,-47.618],[-43.588,-47.618],[-47.871,-45.7],[-47.871,-11.954],[-54.699,-12.898],[-54.699,-12.895],[-60.208999999999996,-15.588],[-79.042,-8.609],[-72.064,15.588],[-56.868,14.468],[-54.295,12.609],[-48.866,11.335],[-47.871,43.335],[-45.953,47.618],[43.083,47.618],[47.366,45.7],[47.366,12.381],[54.699,12.898],[54.699,12.895],[60.208999999999996,15.588],[79.042,8.609]],"o":[[60.027,-15.588],[54.295,-12.593],[50.065,-10.721],[47.366,-12.147],[47.366,-45.7],[43.083,-47.618],[-45.953,-47.618],[-47.871,-43.335],[-50.504000000000005,-10.13],[-54.699,-12.898],[-57.195,-14.593],[-72.064,-15.588],[-79.042,8.609],[-60.027,15.588],[-54.295,12.593],[-50.792,11.046],[-47.871,11.83],[-47.871,45.7],[-43.588,47.618],[45.448,47.618],[47.366,43.335],[49.924,9.744],[54.699,12.898],[57.195,14.593],[72.064,15.588],[79.042,-8.609]],"v":[[63.455,-15.588],[54.295,-12.593],[54.295,-12.609],[47.366,-12.147],[47.366,-43.335],[43.083,-47.618],[-43.588,-47.618],[-47.871,-43.335],[-47.871,-11.954],[-54.699,-12.898],[-54.699,-12.895],[-63.455,-15.588],[-79.042,0],[-63.455,15.588],[-54.295,12.593],[-54.295,12.609],[-47.871,11.83],[-47.871,43.335],[-43.588,47.618],[43.083,47.618],[47.366,43.335],[47.366,12.381],[54.699,12.898],[54.699,12.895],[63.455,15.588],[79.042,0]],"c":true},"ix":2},"nm":"Path 1","mn":"ADBE Vector Shape - Group","hd":false,"_render":true},{"ty":"fl","c":{"a":0,"k":[0.2142,0.1458,0.1458,1],"ix":4},"o":{"a":0,"k":100,"ix":5},"r":1,"bm":0,"nm":"Fill 1","mn":"ADBE Vector Graphic - Fill","hd":false,"_render":true},{"ty":"tr","p":{"a":0,"k":[205.218,255.069],"ix":2},"a":{"a":0,"k":[0,0],"ix":1},"s":{"a":0,"k":[100,100],"ix":3},"r":{"a":0,"k":0,"ix":6},"o":{"a":0,"k":100,"ix":7},"sk":{"a":0,"k":0,"ix":4},"sa":{"a":0,"k":0,"ix":5},"nm":"Transform","_render":true}],"nm":"Group 4","np":2,"cix":2,"bm":0,"ix":4,"mn":"ADBE Vector Group","hd":false,"_render":true},{"ty":"gr","it":[{"ind":0,"ty":"sh","ix":1,"ks":{"a":0,"k":{"i":[[-11.584,0.002],[-6.906,-6.287000000000001],[10.313,-12.109],[7.340999999999999,-1.2799999999999998],[-10.999,11.714]],"o":[[-11.584,0.002],[8.36,-12.641],[12.545,-7.885],[2.8649999999999998,2.378],[-10.999,11.714]],"v":[[-11.584,0.002],[0.727,-9.464],[11.429,-9.997],[5.103,0.549],[-10.999,11.714]],"c":true},"ix":2},"nm":"Path 1","mn":"ADBE Vector Shape - Group","hd":false,"_render":true},{"ty":"fl","c":{"a":0,"k":[1,0.5569,0.2275,1],"ix":4},"o":{"a":0,"k":100,"ix":5},"r":1,"bm":0,"nm":"Fill 1","mn":"ADBE Vector Graphic - Fill","hd":false,"_render":true},{"ty":"tr","p":{"a":0,"k":[207.384,306.247],"ix":2},"a":{"a":0,"k":[0,0],"ix":1},"s":{"a":0,"k":[100,100],"ix":3},"r":{"a":0,"k":0,"ix":6},"o":{"a":0,"k":100,"ix":7},"sk":{"a":0,"k":0,"ix":4},"sa":{"a":0,"k":0,"ix":5},"nm":"Transform","_render":true}],"nm":"Group 5","np":2,"cix":2,"bm":0,"ix":5,"mn":"ADBE Vector Group","hd":false,"_render":true}],"ip":0,"op":120,"st":0,"bm":0,"completed":true},{"ddd":0,"ind":4,"ty":0,"nm":"Pre-comp 1","refId":"comp_0","sr":1,"ks":{"o":{"a":1,"k":[{"i":{"x":[0.19],"y":[1]},"o":{"x":[0.333],"y":[0]},"t":0,"s":[0]},{"t":20,"s":[100]}],"ix":11},"r":{"a":0,"k":0,"ix":10},"p":{"a":1,"k":[{"i":{"x":0.19,"y":1},"o":{"x":0.333,"y":0},"t":0,"s":[-92,381,0],"to":null,"ti":null},{"i":{"x":0.19,"y":0.19},"o":{"x":0.333,"y":0.333},"t":20,"s":[8,381,0],"to":null,"ti":null},{"i":{"x":0.19,"y":1},"o":{"x":0.333,"y":0},"t":70,"s":[8,381,0],"to":null,"ti":null},{"t":85,"s":[21,381,0]}],"ix":2},"a":{"a":0,"k":[8,381,0],"ix":1},"s":{"a":0,"k":[100,100,100],"ix":6}},"ao":0,"w":500,"h":500,"ip":0,"op":120,"st":0,"bm":0,"completed":true,"layers":[{"ddd":0,"ind":1,"ty":4,"nm":"Hand 4","sr":1,"ks":{"o":{"a":0,"k":100,"ix":11},"r":{"a":0,"k":0,"ix":10},"p":{"a":0,"k":[45.084,309.344,0],"ix":2},"a":{"a":0,"k":[45.084,309.344,0],"ix":1},"s":{"a":0,"k":[100,100,100],"ix":6}},"ao":0,"shapes":[{"ty":"gr","it":[{"ty":"gr","it":[{"ind":0,"ty":"sh","ix":1,"ks":{"a":0,"k":{"i":[[-7.175,2.911],[-7.569,2.853],[-7.829000000000001,2.218],[5.487,-2.722],[7.761,-2.737],[7.619,-1.9429999999999998],[-2.9479999999999995,-0.734]],"o":[[-7.431,2.911],[-7.8500000000000005,2.533],[-3.4640000000000004,-1.6109999999999998],[7.516,-2.9379999999999997],[7.818,-2.189],[6.303,-1.8039999999999998],[-7.0569999999999995,2.87]],"v":[[-7.292,2.911],[-7.668,2.741],[-7.621,2.035],[7.239,-2.908],[7.789,-2.463],[7.345,-1.914],[-6.962,2.787]],"c":true},"ix":2},"nm":"Path 1","mn":"ADBE Vector Shape - Group","hd":false,"_render":true},{"ty":"fl","c":{"a":0,"k":[0.8409,0.5339,0.2991,1],"ix":4},"o":{"a":0,"k":100,"ix":5},"r":1,"bm":0,"nm":"Fill 1","mn":"ADBE Vector Graphic - Fill","hd":false,"_render":true},{"ty":"tr","p":{"a":0,"k":[0,0],"ix":2},"a":{"a":0,"k":[0,0],"ix":1},"s":{"a":0,"k":[100,100],"ix":3},"r":{"a":0,"k":0,"ix":6},"o":{"a":0,"k":100,"ix":7},"sk":{"a":0,"k":0,"ix":4},"sa":{"a":0,"k":0,"ix":5},"nm":"Transform","_render":true}],"nm":"Group 1","np":2,"cix":2,"bm":0,"ix":1,"mn":"ADBE Vector Group","hd":false,"_render":true},{"ty":"tr","p":{"a":0,"k":[53.64,271.582],"ix":2},"a":{"a":0,"k":[0,0],"ix":1},"s":{"a":0,"k":[100,100],"ix":3},"r":{"a":0,"k":0,"ix":6},"o":{"a":0,"k":100,"ix":7},"sk":{"a":0,"k":0,"ix":4},"sa":{"a":0,"k":0,"ix":5},"nm":"Transform","_render":true}],"nm":"Group 1","np":1,"cix":2,"bm":0,"ix":1,"mn":"ADBE Vector Group","hd":false,"_render":true},{"ty":"gr","it":[{"ty":"gr","it":[{"ind":0,"ty":"sh","ix":1,"ks":{"a":0,"k":{"i":[[-2.439,1.666],[-2.828,1.6119999999999999],[-3.104,0.9890000000000001],[0.4979999999999998,-1.454],[3.029,-1.492],[2.886,-0.6970000000000001],[-0.9000000000000001,0.29899999999999993]],"o":[[-2.695,1.666],[-3.115,1.3059999999999998],[-1.423,-0.5789999999999998],[2.787,-1.693],[3.086,-0.944],[0.8160000000000001,-0.48200000000000004],[-2.317,1.621]],"v":[[-2.561,1.666],[-2.927,1.507],[-2.902,0.801],[2.509,-1.663],[3.058,-1.218],[2.612,-0.669],[-2.22,1.531]],"c":true},"ix":2},"nm":"Path 1","mn":"ADBE Vector Shape - Group","hd":false,"_render":true},{"ty":"fl","c":{"a":0,"k":[0.8409,0.5339,0.2991,1],"ix":4},"o":{"a":0,"k":100,"ix":5},"r":1,"bm":0,"nm":"Fill 1","mn":"ADBE Vector Graphic - Fill","hd":false,"_render":true},{"ty":"tr","p":{"a":0,"k":[0,0],"ix":2},"a":{"a":0,"k":[0,0],"ix":1},"s":{"a":0,"k":[100,100],"ix":3},"r":{"a":0,"k":0,"ix":6},"o":{"a":0,"k":100,"ix":7},"sk":{"a":0,"k":0,"ix":4},"sa":{"a":0,"k":0,"ix":5},"nm":"Transform","_render":true}],"nm":"Group 1","np":2,"cix":2,"bm":0,"ix":1,"mn":"ADBE Vector Group","hd":false,"_render":true},{"ty":"tr","p":{"a":0,"k":[68.286,302.515],"ix":2},"a":{"a":0,"k":[0,0],"ix":1},"s":{"a":0,"k":[100,100],"ix":3},"r":{"a":0,"k":0,"ix":6},"o":{"a":0,"k":100,"ix":7},"sk":{"a":0,"k":0,"ix":4},"sa":{"a":0,"k":0,"ix":5},"nm":"Transform","_render":true}],"nm":"Group 2","np":1,"cix":2,"bm":0,"ix":2,"mn":"ADBE Vector Group","hd":false,"_render":true},{"ty":"gr","it":[{"ty":"gr","it":[{"ind":0,"ty":"sh","ix":1,"ks":{"a":0,"k":{"i":[[9.056999999999999,4.322],[8.611,4.204],[6.143000000000001,-1.885],[-5.952,-2.8689999999999998],[-9.274,-1.061],[-9.494,-1.8390000000000002],[-0.29000000000000004,-5.027],[8.141,0.3809999999999998],[9.439,4.1819999999999995]],"o":[[8.798,4.322],[7.25,0.847],[-0.34399999999999986,-3.9939999999999998],[-8.966,-0.9899999999999999],[-9.566,-1.53],[-6.294,-3.834],[6.895,-2.692],[9.562999999999999,3.891],[9.121,4.31]],"v":[[8.995,4.322],[8.532,4.01],[2.995,-2.908],[-8.731,-1.136],[-9.42,-1.296],[-9.26,-1.985],[3.304,-3.859],[9.459,3.635],[9.183,4.286]],"c":true},"ix":2},"nm":"Path 1","mn":"ADBE Vector Shape - Group","hd":false,"_render":true},{"ty":"fl","c":{"a":0,"k":[0.8409,0.5339,0.2991,1],"ix":4},"o":{"a":0,"k":100,"ix":5},"r":1,"bm":0,"nm":"Fill 1","mn":"ADBE Vector Graphic - Fill","hd":false,"_render":true},{"ty":"tr","p":{"a":0,"k":[0,0],"ix":2},"a":{"a":0,"k":[0,0],"ix":1},"s":{"a":0,"k":[100,100],"ix":3},"r":{"a":0,"k":0,"ix":6},"o":{"a":0,"k":100,"ix":7},"sk":{"a":0,"k":0,"ix":4},"sa":{"a":0,"k":0,"ix":5},"nm":"Transform","_render":true}],"nm":"Group 1","np":2,"cix":2,"bm":0,"ix":1,"mn":"ADBE Vector Group","hd":false,"_render":true},{"ty":"tr","p":{"a":0,"k":[68.639,292.588],"ix":2},"a":{"a":0,"k":[0,0],"ix":1},"s":{"a":0,"k":[100,100],"ix":3},"r":{"a":0,"k":0,"ix":6},"o":{"a":0,"k":100,"ix":7},"sk":{"a":0,"k":0,"ix":4},"sa":{"a":0,"k":0,"ix":5},"nm":"Transform","_render":true}],"nm":"Group 3","np":1,"cix":2,"bm":0,"ix":3,"mn":"ADBE Vector Group","hd":false,"_render":true},{"ty":"gr","it":[{"ty":"gr","it":[{"ind":0,"ty":"sh","ix":1,"ks":{"a":0,"k":{"i":[[11.786999999999999,2.708],[11.395,2.6519999999999997],[-3.139000000000001,-3.1510000000000002],[-11.949,2.012],[-12.165999999999999,1.234],[6.828999999999999,-3.927],[12.208,2.395]],"o":[[11.530999999999999,2.708],[6.409,-2.8980000000000006],[-11.641,2.086],[-12.238999999999999,1.542],[-3.251999999999999,-4.254],[12.225,2.079],[11.907,2.666]],"v":[[11.668,2.708],[11.296,2.542],[-11.406,1.94],[-12.094,1.776],[-11.931,1.089],[12.04,1.874],[12.002,2.58]],"c":true},"ix":2},"nm":"Path 1","mn":"ADBE Vector Shape - Group","hd":false,"_render":true},{"ty":"fl","c":{"a":0,"k":[0.8409,0.5339,0.2991,1],"ix":4},"o":{"a":0,"k":100,"ix":5},"r":1,"bm":0,"nm":"Fill 1","mn":"ADBE Vector Graphic - Fill","hd":false,"_render":true},{"ty":"tr","p":{"a":0,"k":[0,0],"ix":2},"a":{"a":0,"k":[0,0],"ix":1},"s":{"a":0,"k":[100,100],"ix":3},"r":{"a":0,"k":0,"ix":6},"o":{"a":0,"k":100,"ix":7},"sk":{"a":0,"k":0,"ix":4},"sa":{"a":0,"k":0,"ix":5},"nm":"Transform","_render":true}],"nm":"Group 1","np":2,"cix":2,"bm":0,"ix":1,"mn":"ADBE Vector Group","hd":false,"_render":true},{"ty":"tr","p":{"a":0,"k":[63.292,279.048],"ix":2},"a":{"a":0,"k":[0,0],"ix":1},"s":{"a":0,"k":[100,100],"ix":3},"r":{"a":0,"k":0,"ix":6},"o":{"a":0,"k":100,"ix":7},"sk":{"a":0,"k":0,"ix":4},"sa":{"a":0,"k":0,"ix":5},"nm":"Transform","_render":true}],"nm":"Group 4","np":1,"cix":2,"bm":0,"ix":4,"mn":"ADBE Vector Group","hd":false,"_render":true},{"ty":"gr","it":[{"ty":"gr","it":[{"ind":0,"ty":"sh","ix":1,"ks":{"a":0,"k":{"i":[[1.669,7.064],[1.19,6.891],[-0.807,-4.888],[-0.9209999999999999,-5.556],[-1.391,-6.09],[-2.064,-6.157],[-2.028,-6.965],[-0.536,-6.797],[0.11299999999999999,-5.445],[2.135,6.48],[1.997,7.011]],"o":[[1.401,7.064],[1.148,6.648],[-0.8630000000000001,-5.216],[-1.195,-5.977],[-1.793,-5.997],[-2.193,-6.696],[-1.121,-7.182],[0.030000000000000027,-5.928999999999999],[0.179,-5.056],[2.1809999999999996,6.752000000000001],[1.697,7.062]],"v":[[1.641,7.064],[1.148,6.648],[-0.807,-4.888],[-1.079,-5.798],[-1.525,-6.058],[-2.128,-6.427],[-1.759,-7.03],[-0.241,-6.345],[0.179,-5.056],[2.135,6.48],[1.725,7.057]],"c":true},"ix":2},"nm":"Path 1","mn":"ADBE Vector Shape - Group","hd":false,"_render":true},{"ty":"fl","c":{"a":0,"k":[0.8409,0.5339,0.2991,1],"ix":4},"o":{"a":0,"k":100,"ix":5},"r":1,"bm":0,"nm":"Fill 1","mn":"ADBE Vector Graphic - Fill","hd":false,"_render":true},{"ty":"tr","p":{"a":0,"k":[0,0],"ix":2},"a":{"a":0,"k":[0,0],"ix":1},"s":{"a":0,"k":[100,100],"ix":3},"r":{"a":0,"k":0,"ix":6},"o":{"a":0,"k":100,"ix":7},"sk":{"a":0,"k":0,"ix":4},"sa":{"a":0,"k":0,"ix":5},"nm":"Transform","_render":true}],"nm":"Group 1","np":2,"cix":2,"bm":0,"ix":1,"mn":"ADBE Vector Group","hd":false,"_render":true},{"ty":"tr","p":{"a":0,"k":[65.369,306.95],"ix":2},"a":{"a":0,"k":[0,0],"ix":1},"s":{"a":0,"k":[100,100],"ix":3},"r":{"a":0,"k":0,"ix":6},"o":{"a":0,"k":100,"ix":7},"sk":{"a":0,"k":0,"ix":4},"sa":{"a":0,"k":0,"ix":5},"nm":"Transform","_render":true}],"nm":"Group 5","np":1,"cix":2,"bm":0,"ix":5,"mn":"ADBE Vector Group","hd":false,"_render":true},{"ty":"gr","it":[{"ty":"gr","it":[{"ty":"gr","it":[{"ind":0,"ty":"sh","ix":1,"ks":{"a":0,"k":{"i":[[1.405,-0.505],[0.654,-3.106],[-0.915,-5.305],[0.582,5.462],[1.838,2.776]],"o":[[0.87,-2.242],[-0.216,-4.636],[-1.78,-5.462],[1.2029999999999998,4.151999999999999],[1.736,0.391]],"v":[[1.129,-1.401],[0.219,-3.871],[-1.78,-5.462],[0.582,5.462],[1.776,1.328]],"c":true},"ix":2},"nm":"Path 1","mn":"ADBE Vector Shape - Group","hd":false,"_render":true},{"ty":"fl","c":{"a":0,"k":[0.3333,0,0,1],"ix":4},"o":{"a":0,"k":100,"ix":5},"r":1,"bm":0,"nm":"Fill 1","mn":"ADBE Vector Graphic - Fill","hd":false,"_render":true},{"ty":"tr","p":{"a":0,"k":[0,0],"ix":2},"a":{"a":0,"k":[0,0],"ix":1},"s":{"a":0,"k":[100,100],"ix":3},"r":{"a":0,"k":0,"ix":6},"o":{"a":0,"k":100,"ix":7},"sk":{"a":0,"k":0,"ix":4},"sa":{"a":0,"k":0,"ix":5},"nm":"Transform","_render":true}],"nm":"Group 1","np":2,"cix":2,"bm":0,"ix":1,"mn":"ADBE Vector Group","hd":false,"_render":true},{"ty":"tr","p":{"a":0,"k":[66.426,305.748],"ix":2},"a":{"a":0,"k":[0,0],"ix":1},"s":{"a":0,"k":[100,100],"ix":3},"r":{"a":0,"k":0,"ix":6},"o":{"a":0,"k":100,"ix":7},"sk":{"a":0,"k":0,"ix":4},"sa":{"a":0,"k":0,"ix":5},"nm":"Transform","_render":true}],"nm":"Group 1","np":1,"cix":2,"bm":0,"ix":1,"mn":"ADBE Vector Group","hd":false,"_render":true},{"ty":"tr","p":{"a":0,"k":[66.426,305.748],"ix":2},"a":{"a":0,"k":[66.426,305.748],"ix":1},"s":{"a":0,"k":[100,100],"ix":3},"r":{"a":0,"k":0,"ix":6},"o":{"a":0,"k":100,"ix":7},"sk":{"a":0,"k":0,"ix":4},"sa":{"a":0,"k":0,"ix":5},"nm":"Transform","_render":true}],"nm":"Group 6","np":1,"cix":2,"bm":0,"ix":6,"mn":"ADBE Vector Group","hd":false,"_render":true},{"ty":"gr","it":[{"ty":"gr","it":[{"ind":0,"ty":"sh","ix":1,"ks":{"a":0,"k":{"i":[[-4.763,11.36],[-10.471,-29.202],[6.465000000000001,-72.569],[14.042,-71.456],[4.237,-46.362],[5.574,-37.002],[14.711000000000002,-41.683],[32.763,-33.214],[36.551,-24.076],[34.769,-12.934],[36.551,-6.693],[23.849,1.998],[27.333,19.322000000000003],[5.3420000000000005,73.39500000000001],[-36.79,73.346],[-11.408,23.738]],"o":[[-4.763,11.36],[-11.809000000000001,-49.260000000000005],[10.923000000000002,-73.907],[12.26,-60.757999999999996],[4.237,-46.362],[5.574,-37.002],[30.757,-37.671],[32.094,-28.088],[36.997,-16.054000000000002],[34.769,-12.934],[33.431,-1.791],[23.849,1.998],[18.593,25.213],[5.636,73.346],[-36.79,73.346],[-7.8420000000000005,16.606]],"v":[[-4.763,11.36],[-11.14,-39.231],[8.694,-73.238],[13.151,-66.107],[4.237,-46.362],[5.574,-37.002],[22.734,-39.677],[32.094,-28.088],[36.774,-20.065],[34.769,-12.934],[34.991,-4.242],[23.849,1.998],[18.593,25.213],[5.636,73.346],[-36.79,73.346],[-9.625,20.172]],"c":true},"ix":2},"nm":"Path 1","mn":"ADBE Vector Shape - Group","hd":false,"_render":true},{"ty":"fl","c":{"a":0,"k":[0.9925,0.831,0.7075,1],"ix":4},"o":{"a":0,"k":100,"ix":5},"r":1,"bm":0,"nm":"Fill 1","mn":"ADBE Vector Graphic - Fill","hd":false,"_render":true},{"ty":"tr","p":{"a":0,"k":[0,0],"ix":2},"a":{"a":0,"k":[0,0],"ix":1},"s":{"a":0,"k":[100,100],"ix":3},"r":{"a":0,"k":0,"ix":6},"o":{"a":0,"k":100,"ix":7},"sk":{"a":0,"k":0,"ix":4},"sa":{"a":0,"k":0,"ix":5},"nm":"Transform","_render":true}],"nm":"Group 1","np":2,"cix":2,"bm":0,"ix":1,"mn":"ADBE Vector Group","hd":false,"_render":true},{"ty":"tr","p":{"a":0,"k":[42.866,309.344],"ix":2},"a":{"a":0,"k":[0,0],"ix":1},"s":{"a":0,"k":[100,100],"ix":3},"r":{"a":0,"k":0,"ix":6},"o":{"a":0,"k":100,"ix":7},"sk":{"a":0,"k":0,"ix":4},"sa":{"a":0,"k":0,"ix":5},"nm":"Transform","_render":true}],"nm":"Group 7","np":1,"cix":2,"bm":0,"ix":7,"mn":"ADBE Vector Group","hd":false,"_render":true},{"ty":"gr","it":[{"ty":"gr","it":[{"ind":0,"ty":"sh","ix":1,"ks":{"a":0,"k":{"i":[[-4.979,-15.37],[0.9310000000000003,-14.985],[3.479,-6.061],[9.467,-1.9240000000000004],[5.155,10.779],[7.363,15.37],[-3.834,15.193],[-8.032,-7.127]],"o":[[-4.979,-15.37],[2.837,-8.879],[3.479,-6.061],[7.304,7.596],[5.155,10.779],[7.363,15.37],[-3.834,15.193],[-8.032,-7.127]],"v":[[-4.979,-15.37],[2.837,-8.879],[3.479,-6.061],[7.708,5.819],[5.155,10.779],[7.363,15.37],[-3.834,15.193],[-8.032,-7.127]],"c":true},"ix":2},"nm":"Path 1","mn":"ADBE Vector Shape - Group","hd":false,"_render":true},{"ty":"fl","c":{"a":0,"k":[0.3333,0,0,1],"ix":4},"o":{"a":0,"k":100,"ix":5},"r":1,"bm":0,"nm":"Fill 1","mn":"ADBE Vector Graphic - Fill","hd":false,"_render":true},{"ty":"tr","p":{"a":0,"k":[0,0],"ix":2},"a":{"a":0,"k":[0,0],"ix":1},"s":{"a":0,"k":[100,100],"ix":3},"r":{"a":0,"k":0,"ix":6},"o":{"a":0,"k":100,"ix":7},"sk":{"a":0,"k":0,"ix":4},"sa":{"a":0,"k":0,"ix":5},"nm":"Transform","_render":true}],"nm":"Group 1","np":2,"cix":2,"bm":0,"ix":1,"mn":"ADBE Vector Group","hd":false,"_render":true},{"ty":"tr","p":{"a":0,"k":[76.06,287.317],"ix":2},"a":{"a":0,"k":[0,0],"ix":1},"s":{"a":0,"k":[100,100],"ix":3},"r":{"a":0,"k":0,"ix":6},"o":{"a":0,"k":100,"ix":7},"sk":{"a":0,"k":0,"ix":4},"sa":{"a":0,"k":0,"ix":5},"nm":"Transform","_render":true}],"nm":"Group 8","np":1,"cix":2,"bm":0,"ix":8,"mn":"ADBE Vector Group","hd":false,"_render":true},{"ty":"gr","it":[{"ty":"gr","it":[{"ind":0,"ty":"sh","ix":1,"ks":{"a":0,"k":{"i":[[-1.765,-14.012],[1.408,-14.181],[-2.733,14.013],[-2.733,-2.087]],"o":[[-1.765,-14.012],[3.772,-3.712999999999999],[-2.733,14.013],[-2.733,-2.087]],"v":[[-1.765,-14.012],[2.59,-8.947],[-2.733,14.013],[-2.733,-2.087]],"c":true},"ix":2},"nm":"Path 1","mn":"ADBE Vector Shape - Group","hd":false,"_render":true},{"ty":"fl","c":{"a":0,"k":[0.3333,0,0,1],"ix":4},"o":{"a":0,"k":100,"ix":5},"r":1,"bm":0,"nm":"Fill 1","mn":"ADBE Vector Graphic - Fill","hd":false,"_render":true},{"ty":"tr","p":{"a":0,"k":[0,0],"ix":2},"a":{"a":0,"k":[0,0],"ix":1},"s":{"a":0,"k":[100,100],"ix":3},"r":{"a":0,"k":0,"ix":6},"o":{"a":0,"k":100,"ix":7},"sk":{"a":0,"k":0,"ix":4},"sa":{"a":0,"k":0,"ix":5},"nm":"Transform","_render":true}],"nm":"Group 1","np":2,"cix":2,"bm":0,"ix":1,"mn":"ADBE Vector Group","hd":false,"_render":true},{"ty":"tr","p":{"a":0,"k":[55.406,251.404],"ix":2},"a":{"a":0,"k":[0,0],"ix":1},"s":{"a":0,"k":[100,100],"ix":3},"r":{"a":0,"k":0,"ix":6},"o":{"a":0,"k":100,"ix":7},"sk":{"a":0,"k":0,"ix":4},"sa":{"a":0,"k":0,"ix":5},"nm":"Transform","_render":true}],"nm":"Group 9","np":1,"cix":2,"bm":0,"ix":9,"mn":"ADBE Vector Group","hd":false,"_render":true}],"ip":0,"op":120,"st":0,"bm":0,"completed":true},{"ddd":0,"ind":2,"ty":4,"nm":"Hand 3","sr":1,"ks":{"o":{"a":0,"k":100,"ix":11},"r":{"a":0,"k":0,"ix":10},"p":{"a":0,"k":[95.358,255.069,0],"ix":2},"a":{"a":0,"k":[95.358,255.069,0],"ix":1},"s":{"a":0,"k":[100,100,100],"ix":6}},"ao":0,"shapes":[{"ty":"gr","it":[{"ty":"gr","it":[{"ind":0,"ty":"sh","ix":1,"ks":{"a":0,"k":{"i":[[10.27,-16.058],[-15.953,3.2250000000000014],[-0.732,16.236],[-12.094000000000001,15.609],[14.704,-16.273]],"o":[[9.418,-16.236],[-14.667,16.236],[-0.732,16.236],[-0.5179999999999998,-3.3390000000000004],[14.718,-15.767000000000001]],"v":[[9.418,-16.236],[-14.667,16.236],[-0.732,16.236],[-6.306,6.135],[14.715,-15.874]],"c":true},"ix":2},"nm":"Path 1","mn":"ADBE Vector Shape - Group","hd":false,"_render":true},{"ty":"fl","c":{"a":0,"k":[1,1,1,1],"ix":4},"o":{"a":0,"k":100,"ix":5},"r":1,"bm":0,"nm":"Fill 1","mn":"ADBE Vector Graphic - Fill","hd":false,"_render":true},{"ty":"tr","p":{"a":0,"k":[0,0],"ix":2},"a":{"a":0,"k":[0,0],"ix":1},"s":{"a":0,"k":[100,100],"ix":3},"r":{"a":0,"k":0,"ix":6},"o":{"a":0,"k":100,"ix":7},"sk":{"a":0,"k":0,"ix":4},"sa":{"a":0,"k":0,"ix":5},"nm":"Transform","_render":true}],"nm":"Group 1","np":2,"cix":2,"bm":0,"ix":1,"mn":"ADBE Vector Group","hd":false,"_render":true},{"ty":"tr","p":{"a":0,"k":[118.459,286.451],"ix":2},"a":{"a":0,"k":[0,0],"ix":1},"s":{"a":0,"k":[100,100],"ix":3},"r":{"a":0,"k":0,"ix":6},"o":{"a":0,"k":100,"ix":7},"sk":{"a":0,"k":0,"ix":4},"sa":{"a":0,"k":0,"ix":5},"nm":"Transform","_render":true}],"nm":"Group 1","np":1,"cix":2,"bm":0,"ix":1,"mn":"ADBE Vector Group","hd":false,"_render":true},{"ty":"gr","it":[{"ty":"gr","it":[{"ind":0,"ty":"sh","ix":1,"ks":{"a":0,"k":{"i":[[23.195,-42.568],[27.910000000000004,-34.146],[-6.034000000000001,-2.4640000000000004],[-42.619,23.183],[-42.619,42.568],[-10.937999999999999,38.534],[1.9639999999999986,-4.915000000000001],[42.619,-42.568],[23.195,-42.568]],"o":[[23.195,-42.568],[6.412000000000001,-19.436],[-10.938,20.542],[-42.619,23.183],[-42.619,42.568],[1.1320000000000006,9.416000000000002],[22.064,-24.905],[42.619,-42.568],[23.195,-42.568]],"v":[[23.195,-42.568],[17.161,-26.791],[-8.486,9.039],[-42.619,23.183],[-42.619,42.568],[-4.903,23.975],[12.014,-14.91],[42.619,-42.568],[23.195,-42.568]],"c":false},"ix":2},"nm":"Path 1","mn":"ADBE Vector Shape - Group","hd":false,"_render":true},{"ty":"fl","c":{"a":0,"k":[1,1,1,1],"ix":4},"o":{"a":0,"k":100,"ix":5},"r":1,"bm":0,"nm":"Fill 1","mn":"ADBE Vector Graphic - Fill","hd":false,"_render":true},{"ty":"tr","p":{"a":0,"k":[0,0],"ix":2},"a":{"a":0,"k":[0,0],"ix":1},"s":{"a":0,"k":[100,100],"ix":3},"r":{"a":0,"k":0,"ix":6},"o":{"a":0,"k":100,"ix":7},"sk":{"a":0,"k":0,"ix":4},"sa":{"a":0,"k":0,"ix":5},"nm":"Transform","_render":true}],"nm":"Group 1","np":2,"cix":2,"bm":0,"ix":1,"mn":"ADBE Vector Group","hd":false,"_render":true},{"ty":"tr","p":{"a":0,"k":[95.358,250.018],"ix":2},"a":{"a":0,"k":[0,0],"ix":1},"s":{"a":0,"k":[100,100],"ix":3},"r":{"a":0,"k":0,"ix":6},"o":{"a":0,"k":100,"ix":7},"sk":{"a":0,"k":0,"ix":4},"sa":{"a":0,"k":0,"ix":5},"nm":"Transform","_render":true}],"nm":"Group 2","np":1,"cix":2,"bm":0,"ix":2,"mn":"ADBE Vector Group","hd":false,"_render":true}],"ip":0,"op":120,"st":0,"bm":0,"completed":true},{"ddd":0,"ind":3,"ty":4,"nm":"Hand 2","sr":1,"ks":{"o":{"a":0,"k":100,"ix":11},"r":{"a":0,"k":0,"ix":10},"p":{"a":0,"k":[100.291,239.39,0],"ix":2},"a":{"a":0,"k":[0,0,0],"ix":1},"s":{"a":0,"k":[100,100,100],"ix":6}},"ao":0,"shapes":[{"ty":"gr","it":[{"ind":0,"ty":"sh","ix":1,"ks":{"a":0,"k":{"i":[[45.117000000000004,6.090999999999999],[47.618,-27.657],[45.7,-31.94],[10.031,-31.94],[10.849,-38.954],[10.847,-38.954],[13.538,-44.464],[6.5600000000000005,-63.297],[-17.637,-56.319],[-16.531000000000002,-41.121],[-13.427,-32.873000000000005],[-43.335,-31.94],[-47.618,-30.022],[-47.618,59.014],[-45.7,63.297],[43.335,63.297],[47.618,61.379000000000005],[47.618,27.998],[45.143,26.215],[40.497,28.272],[34.766,31.266],[15.75,24.288],[22.729,0.091],[37.597,1.085],[40.093,2.781]],"o":[[47.618,3.066],[47.618,-30.022],[43.335,-31.94],[7.939,-34.556000000000004],[10.849,-38.954],[12.545,-41.45],[13.538,-56.319],[-10.658,-63.297],[-17.637,-44.286],[-12.995000000000001,-34.821],[-13.975,-31.94],[-45.7,-31.94],[-47.618,-27.657],[-47.618,61.379000000000005],[-43.335,63.297],[45.7,63.297],[47.618,59.014],[47.022000000000006,27.394000000000002],[40.498,28.288],[37.924,30.147],[22.729,31.266],[15.75,7.07],[34.584,0.091],[40.093,2.783],[40.093,2.781]],"v":[[47.618,3.066],[47.618,-27.657],[43.335,-31.94],[10.031,-31.94],[10.849,-38.954],[10.847,-38.954],[13.538,-47.71],[-2.049,-63.297],[-17.637,-47.71],[-14.659,-38.549],[-13.975,-31.94],[-43.335,-31.94],[-47.618,-27.657],[-47.618,59.014],[-43.335,63.297],[43.335,63.297],[47.618,59.014],[47.618,27.998],[40.498,28.288],[40.497,28.272],[31.338,31.266],[15.75,15.679],[31.338,0.091],[40.093,2.783],[40.093,2.781]],"c":true},"ix":2},"nm":"Path 1","mn":"ADBE Vector Shape - Group","hd":false,"_render":true},{"ty":"fl","c":{"a":0,"k":[1,0.26,0.556,1],"ix":4},"o":{"a":0,"k":100,"ix":5},"r":1,"bm":0,"nm":"Fill 1","mn":"ADBE Vector Graphic - Fill","hd":false,"_render":true},{"ty":"tr","p":{"a":0,"k":[0,0],"ix":2},"a":{"a":0,"k":[0,0],"ix":1},"s":{"a":0,"k":[100,100],"ix":3},"r":{"a":0,"k":0,"ix":6},"o":{"a":0,"k":100,"ix":7},"sk":{"a":0,"k":0,"ix":4},"sa":{"a":0,"k":0,"ix":5},"nm":"Transform","_render":true}],"nm":"Group 1","np":2,"cix":2,"bm":0,"ix":1,"mn":"ADBE Vector Group","hd":false,"_render":true}],"ip":0,"op":120,"st":0,"bm":0,"completed":true}]}],"markers":[],"__complete":true}